{"data":[{"id":"4428_4465_4861_28503","label":"汾阳市石庄镇卫生院","votes":"","isClick":true},{"id":"4428_4465_4861_28504","label":"汾阳市石庄镇谷雨墕村卫生室","votes":"","isClick":true},{"id":"4428_4465_4861_28505","label":"汾阳市石庄镇后杨寨村卫生室","votes":"","isClick":true},{"id":"4428_4465_4861_28506","label":"汾阳市石庄镇菽禾村卫生室","votes":"","isClick":true},{"id":"4428_4465_4861_28507","label":"汾阳市石庄镇李家庄村卫生室","votes":"","isClick":true},{"id":"4428_4465_4861_28508","label":"汾阳市石庄镇曹家庄村卫生室","votes":"","isClick":true},{"id":"4428_4465_4861_28509","label":"汾阳市石庄镇北广城村卫生室","votes":"","isClick":true},{"id":"4428_4465_4861_28510","label":"汾阳市石庄镇西武堡村卫生室","votes":"","isClick":true},{"id":"4428_4465_4861_28511","label":"汾阳市石庄镇南广城村王达仁卫生室","votes":"","isClick":true},{"id":"4428_4465_4861_28512","label":"汾阳市石庄镇胡家社村卫生室","votes":"","isClick":true},{"id":"4428_4465_4861_28513","label":"汾阳市石庄镇张家庄村卫生室","votes":"","isClick":true},{"id":"4428_4465_4861_28514","label":"汾阳市石庄镇原家社村卫生室","votes":"","isClick":true},{"id":"4428_4465_4861_28515","label":"汾阳市石庄镇阳泉村卫生室","votes":"","isClick":true},{"id":"4428_4465_4861_28516","label":"汾阳市石庄镇东村卫生室","votes":"","isClick":true},{"id":"4428_4465_4861_28517","label":"汾阳市石庄镇下庄村卫生室","votes":"","isClick":true},{"id":"4428_4465_4861_28518","label":"汾阳市石庄镇南广城村孔令军卫生室","votes":"","isClick":true},{"id":"4428_4465_4861_28519","label":"汾阳市石庄镇石庄村卫生室","votes":"","isClick":true}]}