{"data":[{"id":"4428_4460_4805_27298","label":"孝义市高阳镇卫生院","votes":"","isClick":true},{"id":"4428_4460_4805_27299","label":"孝义市高阳镇大垣村卫生室","votes":"","isClick":true},{"id":"4428_4460_4805_27300","label":"孝义市高阳镇小垣村卫生室","votes":"","isClick":true},{"id":"4428_4460_4805_27301","label":"孝义市高阳镇善吉村卫生室","votes":"","isClick":true},{"id":"4428_4460_4805_27302","label":"孝义市高阳镇下吐京村卫生室","votes":"","isClick":true},{"id":"4428_4460_4805_27303","label":"孝义市高阳镇白璧关村卫生室","votes":"","isClick":true},{"id":"4428_4460_4805_27304","label":"孝义市高阳镇顺光村卫生室","votes":"","isClick":true},{"id":"4428_4460_4805_27305","label":"孝义市高阳镇临水村卫生室","votes":"","isClick":true},{"id":"4428_4460_4805_27306","label":"孝义市高阳镇高阳村卫生室","votes":"","isClick":true},{"id":"4428_4460_4805_27307","label":"孝义市高阳镇三多村卫生室","votes":"","isClick":true},{"id":"4428_4460_4805_27308","label":"孝义市高阳镇神福村卫生室","votes":"","isClick":true},{"id":"4428_4460_4805_27309","label":"孝义市高阳镇贤者村卫生室","votes":"","isClick":true},{"id":"4428_4460_4805_27310","label":"孝义市高阳镇神安村卫生室","votes":"","isClick":true},{"id":"4428_4460_4805_27311","label":"孝义市高阳镇西曹村卫生室","votes":"","isClick":true},{"id":"4428_4460_4805_27312","label":"孝义市高阳镇东曹村卫生室","votes":"","isClick":true},{"id":"4428_4460_4805_27313","label":"孝义市高阳镇西辛壁村卫生室","votes":"","isClick":true},{"id":"4428_4460_4805_27314","label":"孝义市高阳镇东辛壁村卫生室","votes":"","isClick":true},{"id":"4428_4460_4805_27315","label":"孝义市高阳镇仁义村卫生室","votes":"","isClick":true},{"id":"4428_4460_4805_27316","label":"孝义市-山西汾西矿业集团责任公司高阳煤矿职工医院","votes":"","isClick":true}]}