{"data":[{"id":"4428_4463_4835_27948","label":"方山县马坊镇中心卫生院","votes":"","isClick":true},{"id":"4428_4463_4835_27949","label":"杨家坪村卫生所","votes":"","isClick":true},{"id":"4428_4463_4835_27950","label":"赤街村卫生所","votes":"","isClick":true},{"id":"4428_4463_4835_27951","label":"窑上村卫生所","votes":"","isClick":true},{"id":"4428_4463_4835_27952","label":"温家庄村卫生所","votes":"","isClick":true},{"id":"4428_4463_4835_27953","label":"李家湾村卫生所","votes":"","isClick":true},{"id":"4428_4463_4835_27954","label":"龙泉村卫生所","votes":"","isClick":true},{"id":"4428_4463_4835_27955","label":"树林则村卫生所","votes":"","isClick":true},{"id":"4428_4463_4835_27956","label":"周家沟村卫生所","votes":"","isClick":true},{"id":"4428_4463_4835_27957","label":"赤街会村卫生所","votes":"","isClick":true},{"id":"4428_4463_4835_27958","label":"马坊村第三卫生所","votes":"","isClick":true},{"id":"4428_4463_4835_27959","label":"四皓村卫生所","votes":"","isClick":true},{"id":"4428_4463_4835_27960","label":"马坊村第一卫生所","votes":"","isClick":true},{"id":"4428_4463_4835_27961","label":"马坊村第二村卫生所","votes":"","isClick":true},{"id":"4428_4463_4835_27962","label":"庄则上村卫生所","votes":"","isClick":true},{"id":"4428_4463_4835_27963","label":"代坡村卫生所","votes":"","isClick":true},{"id":"4428_4463_4835_27964","label":"方山县马坊镇卫生院开府分院","votes":"","isClick":true},{"id":"4428_4463_4835_27965","label":"方山县马坊镇西沟村卫生室","votes":"","isClick":true},{"id":"4428_4463_4835_27966","label":"方山县马坊镇王家湾村","votes":"","isClick":true},{"id":"4428_4463_4835_27967","label":"方山县马坊镇赤坚岭一所村卫生室","votes":"","isClick":true},{"id":"4428_4463_4835_27968","label":"开府第一村卫生室","votes":"","isClick":true},{"id":"4428_4463_4835_27969","label":"方山县马坊镇麻峪村","votes":"","isClick":true},{"id":"4428_4463_4835_27970","label":"方山县马坊镇里其村","votes":"","isClick":true},{"id":"4428_4463_4835_27971","label":"方山县马坊镇条则焉村卫生室","votes":"","isClick":true},{"id":"4428_4463_4835_27972","label":"方山县马坊镇赤坚岭村第二村卫生室","votes":"","isClick":true},{"id":"4428_4463_4835_27973","label":"方山县马坊镇高明村卫生室","votes":"","isClick":true},{"id":"4428_4463_4835_27974","label":"方山县马坊镇吴家沟村卫生室","votes":"","isClick":true},{"id":"4428_4463_4835_27975","label":"方山县马坊镇辉回村卫生室","votes":"","isClick":true},{"id":"4428_4463_4835_27976","label":"方山县马坊镇同堡村卫生室","votes":"","isClick":true},{"id":"4428_4463_4835_27977","label":"方山县马坊镇落辉村卫生室","votes":"","isClick":true},{"id":"4428_4463_4835_27978","label":"方山县马坊镇杨家沟村卫生室","votes":"","isClick":true},{"id":"4428_4463_4835_27979","label":"方山县马坊镇油坊沟村卫生室","votes":"","isClick":true},{"id":"4428_4463_4835_27980","label":"方山县马坊镇磨地湾村卫生室","votes":"","isClick":true},{"id":"4428_4463_4835_27981","label":"方山县马坊镇开府村第二卫生室","votes":"","isClick":true},{"id":"4428_4463_4835_27982","label":"方山县马坊镇红崖湾村卫生室","votes":"","isClick":true}]}