{"data":[{"id":"4428_4465_4852_28265","label":"汾阳市三泉中心卫生院","votes":"","isClick":true},{"id":"4428_4465_4852_28266","label":"汾阳市三泉镇三泉村路仁忠卫生室","votes":"","isClick":true},{"id":"4428_4465_4852_28267","label":"汾阳市三泉镇三泉村郝德华卫生室","votes":"","isClick":true},{"id":"4428_4465_4852_28268","label":"汾阳市三泉镇张新堡村赵学俊卫生室","votes":"","isClick":true},{"id":"4428_4465_4852_28269","label":"汾阳市三泉镇赵家堡村田仲禹卫生室","votes":"","isClick":true},{"id":"4428_4465_4852_28270","label":"汾阳市三泉镇任家堡村卫生室","votes":"","isClick":true},{"id":"4428_4465_4852_28271","label":"汾阳市三泉镇李家街村梁海霞卫生室","votes":"","isClick":true},{"id":"4428_4465_4852_28272","label":"汾阳市三泉镇南垣村卫生室","votes":"","isClick":true},{"id":"4428_4465_4852_28273","label":"汾阳市三泉镇仁道村高昌云卫生室","votes":"","isClick":true},{"id":"4428_4465_4852_28274","label":"汾阳市三泉镇郭家庄村马小东卫生室","votes":"","isClick":true},{"id":"4428_4465_4852_28275","label":"汾阳市三泉镇新贤村卫生室","votes":"","isClick":true},{"id":"4428_4465_4852_28276","label":"汾阳市三泉镇团城村郎丽君卫生室","votes":"","isClick":true},{"id":"4428_4465_4852_28277","label":"汾阳市三泉镇段家庄村卫生室","votes":"","isClick":true},{"id":"4428_4465_4852_28278","label":"汾阳市三泉镇聂生村卫生室","votes":"","isClick":true},{"id":"4428_4465_4852_28279","label":"汾阳市三泉镇巩村卫生室","votes":"","isClick":true},{"id":"4428_4465_4852_28280","label":"汾阳市三泉镇义丰南村田援苹卫生室","votes":"","isClick":true},{"id":"4428_4465_4852_28281","label":"汾阳市三泉镇义丰南村雷化纵变卫生室","votes":"","isClick":true},{"id":"4428_4465_4852_28282","label":"汾阳市三泉镇义丰南村田晓东卫生室","votes":"","isClick":true},{"id":"4428_4465_4852_28283","label":"汾阳市三泉镇平陆村贺照明卫生室","votes":"","isClick":true},{"id":"4428_4465_4852_28284","label":"汾阳市三泉镇平陆村郭志红卫生室","votes":"","isClick":true},{"id":"4428_4465_4852_28285","label":"汾阳市三泉镇西赵村卫生室","votes":"","isClick":true},{"id":"4428_4465_4852_28286","label":"汾阳市三泉镇东赵村卫生室","votes":"","isClick":true},{"id":"4428_4465_4852_28287","label":"汾阳市三泉镇东石村韩汝发卫生室","votes":"","isClick":true},{"id":"4428_4465_4852_28288","label":"汾阳市三泉镇南石村卫生室","votes":"","isClick":true},{"id":"4428_4465_4852_28289","label":"汾阳市三泉镇北石村卫生室","votes":"","isClick":true},{"id":"4428_4465_4852_28290","label":"汾阳市三泉镇上庄村卫生室","votes":"","isClick":true},{"id":"4428_4465_4852_28291","label":"汾阳市三泉镇北马庄村李广宏卫生室","votes":"","isClick":true},{"id":"4428_4465_4852_28292","label":"汾阳市三泉镇南马庄村张丽红卫生室","votes":"","isClick":true},{"id":"4428_4465_4852_28293","label":"汾阳市三泉镇南马庄村王兆坤卫生室","votes":"","isClick":true},{"id":"4428_4465_4852_28294","label":"汾阳市三泉镇北榆苑村靳云文卫生室","votes":"","isClick":true},{"id":"4428_4465_4852_28295","label":"汾阳市三泉镇北榆苑村张丽芬卫生室","votes":"","isClick":true},{"id":"4428_4465_4852_28296","label":"汾阳市三泉镇仁义庄村卫生室","votes":"","isClick":true},{"id":"4428_4465_4852_28297","label":"汾阳市三泉镇西贾壁村卫生室","votes":"","isClick":true},{"id":"4428_4465_4852_28298","label":"汾阳市三泉镇东贾壁村卫生室","votes":"","isClick":true},{"id":"4428_4465_4852_28299","label":"汾阳市三泉镇岅峪村卫生室","votes":"","isClick":true},{"id":"4428_4465_4852_28300","label":"汾阳市三泉镇崞村辛世杰卫生室","votes":"","isClick":true},{"id":"4428_4465_4852_28301","label":"汾阳市三泉镇员庄村史海军卫生室","votes":"","isClick":true}]}