{"data":[{"id":"4429_4476_5005_30561","label":"灵丘县东河南中心卫生院","votes":"","isClick":true},{"id":"4429_4476_5005_30562","label":"灵丘县东河南镇蔡家峪村卫生室","votes":"","isClick":true},{"id":"4429_4476_5005_30563","label":"灵丘县东河南镇成才沟村卫生室","votes":"","isClick":true},{"id":"4429_4476_5005_30564","label":"灵丘县东河南镇水涧村卫生室","votes":"","isClick":true},{"id":"4429_4476_5005_30565","label":"灵丘县东河南镇中野窝村卫生室","votes":"","isClick":true},{"id":"4429_4476_5005_30566","label":"灵丘县东河南镇小寨村卫生室","votes":"","isClick":true},{"id":"4429_4476_5005_30567","label":"灵丘县东河南镇北张庄村卫生室","votes":"","isClick":true},{"id":"4429_4476_5005_30568","label":"灵丘县东河南镇燕家湾村卫生室","votes":"","isClick":true},{"id":"4429_4476_5005_30569","label":"灵丘县东河南镇南元村卫生室","votes":"","isClick":true},{"id":"4429_4476_5005_30570","label":"灵丘县东河南镇古之河村卫生室","votes":"","isClick":true},{"id":"4429_4476_5005_30571","label":"灵丘县东河南镇古之山村卫生室","votes":"","isClick":true},{"id":"4429_4476_5005_30572","label":"灵丘县东河南镇清泥涧村卫生室","votes":"","isClick":true},{"id":"4429_4476_5005_30573","label":"灵丘县东河南镇东窖村卫生室","votes":"","isClick":true},{"id":"4429_4476_5005_30574","label":"灵丘县东河南镇六合地村卫生室","votes":"","isClick":true},{"id":"4429_4476_5005_30575","label":"灵丘县东河南镇下野窝村卫生室","votes":"","isClick":true},{"id":"4429_4476_5005_30576","label":"灵丘县东河南镇大北地村卫生室","votes":"","isClick":true},{"id":"4429_4476_5005_30577","label":"灵丘县东河南镇鹅鸭泉村卫生室","votes":"","isClick":true},{"id":"4429_4476_5005_30578","label":"灵丘县东河南镇亭之岭村卫生室","votes":"","isClick":true},{"id":"4429_4476_5005_30579","label":"灵丘县东河南镇王品村卫生室","votes":"","isClick":true},{"id":"4429_4476_5005_30580","label":"灵丘县东河南镇古树村卫生室","votes":"","isClick":true},{"id":"4429_4476_5005_30581","label":"灵丘县东河南镇三合地村卫生室","votes":"","isClick":true},{"id":"4429_4476_5005_30582","label":"灵丘县东河南镇峰北村卫生室","votes":"","isClick":true},{"id":"4429_4476_5005_30583","label":"灵丘县东河南镇古之河村第二卫生室","votes":"","isClick":true},{"id":"4429_4476_5005_30584","label":"灵丘县东河南中心卫生院银厂分院","votes":"","isClick":true},{"id":"4429_4476_5005_30585","label":"灵丘县东河南镇东岗村卫生室","votes":"","isClick":true},{"id":"4429_4476_5005_30586","label":"灵丘县东河南镇水泉村卫生室","votes":"","isClick":true},{"id":"4429_4476_5005_30587","label":"灵丘县东河南镇阳山沟村卫生室","votes":"","isClick":true},{"id":"4429_4476_5005_30588","label":"灵丘县东河南镇野里村卫生室","votes":"","isClick":true},{"id":"4429_4476_5005_30589","label":"灵丘县东河南镇蒜玉门村卫生室","votes":"","isClick":true}]}