{"data":[{"id":"4429_4477_5019_30866","label":"阳高县古城卫生院","votes":"","isClick":true},{"id":"4429_4477_5019_30867","label":"阳高县古城镇单家窑村卫生室","votes":"","isClick":true},{"id":"4429_4477_5019_30868","label":"阳高县古城镇东靳家洼卫生室","votes":"","isClick":true},{"id":"4429_4477_5019_30869","label":"阳高县古城镇许家窑村卫生室","votes":"","isClick":true},{"id":"4429_4477_5019_30870","label":"阳高县古城镇郝家窑村卫生室","votes":"","isClick":true},{"id":"4429_4477_5019_30871","label":"阳高县古城镇昝娘城村卫生室","votes":"","isClick":true},{"id":"4429_4477_5019_30872","label":"阳高县古城镇靳娘城村卫生室","votes":"","isClick":true},{"id":"4429_4477_5019_30873","label":"阳高县古城镇鲁家湾村卫生室","votes":"","isClick":true},{"id":"4429_4477_5019_30874","label":"阳高县古城镇上娘城村卫生室","votes":"","isClick":true},{"id":"4429_4477_5019_30875","label":"阳高县古城镇赵家村卫生室","votes":"","isClick":true},{"id":"4429_4477_5019_30876","label":"阳高县古城镇上辛庄村卫生室","votes":"","isClick":true},{"id":"4429_4477_5019_30877","label":"阳高县古城镇寺塔村卫生室","votes":"","isClick":true},{"id":"4429_4477_5019_30878","label":"阳高县古城镇西要泉村卫生室","votes":"","isClick":true},{"id":"4429_4477_5019_30879","label":"阳高县古城镇水泉洼村卫生室","votes":"","isClick":true},{"id":"4429_4477_5019_30880","label":"阳高县古城镇下辛庄村卫生室","votes":"","isClick":true},{"id":"4429_4477_5019_30881","label":"阳高县古城镇新山庄村卫生室","votes":"","isClick":true},{"id":"4429_4477_5019_30882","label":"阳高县古城镇西靳家洼卫生室","votes":"","isClick":true},{"id":"4429_4477_5019_30883","label":"阳高县古城镇下娘城村卫生室","votes":"","isClick":true},{"id":"4429_4477_5019_30884","label":"阳高县古城卫生院下神峪分院","votes":"","isClick":true},{"id":"4429_4477_5019_30885","label":"阳高县古城镇东雷庄村卫生室","votes":"","isClick":true},{"id":"4429_4477_5019_30886","label":"阳高县古城镇箭插村卫生室","votes":"","isClick":true},{"id":"4429_4477_5019_30887","label":"阳高县古城镇彭家窑村卫生室","votes":"","isClick":true},{"id":"4429_4477_5019_30888","label":"阳高县古城镇靳家窑村卫生室","votes":"","isClick":true},{"id":"4429_4477_5019_30889","label":"阳高县古城镇上神峪村卫生室","votes":"","isClick":true},{"id":"4429_4477_5019_30890","label":"阳高县古城镇赵石庄村卫生室","votes":"","isClick":true},{"id":"4429_4477_5019_30891","label":"阳高县古城镇麦早村卫生室","votes":"","isClick":true},{"id":"4429_4477_5019_30892","label":"阳高县古城镇南仁窑村卫生室","votes":"","isClick":true},{"id":"4429_4477_5019_30893","label":"阳高县古城镇碾儿屯村卫生室","votes":"","isClick":true},{"id":"4429_4477_5019_30894","label":"阳高县古城镇西雷庄村卫生室","votes":"","isClick":true}]}