{"data":[{"id":"4429_4472_4962_29864","label":"大同市南郊区新旺乡卫生院","votes":"","isClick":true},{"id":"4429_4472_4962_29865","label":"南郊区新旺乡五爱村卫生室","votes":"","isClick":true},{"id":"4429_4472_4962_29866","label":"南郊区新旺乡永久村卫生室","votes":"","isClick":true},{"id":"4429_4472_4962_29867","label":"南郊区新旺乡解放村卫生室","votes":"","isClick":true},{"id":"4429_4472_4962_29868","label":"南郊区新旺乡红旗村卫生室","votes":"","isClick":true},{"id":"4429_4472_4962_29869","label":"南郊区新旺乡新华村卫生室","votes":"","isClick":true},{"id":"4429_4472_4962_29870","label":"南郊区新旺乡先锋村卫生室","votes":"","isClick":true},{"id":"4429_4472_4962_29871","label":"南郊区新旺乡和平村卫生室","votes":"","isClick":true},{"id":"4429_4472_4962_29872","label":"南郊区新旺乡新民村卫生室","votes":"","isClick":true},{"id":"4429_4472_4962_29873","label":"南郊区新旺乡永宁村卫生室","votes":"","isClick":true},{"id":"4429_4472_4962_29874","label":"南郊区新旺乡新旺村卫生室","votes":"","isClick":true},{"id":"4429_4472_4962_29875","label":"南郊区新旺乡新中村卫生室","votes":"","isClick":true},{"id":"4429_4472_4962_29876","label":"南郊区新旺乡新泉村卫生室","votes":"","isClick":true},{"id":"4429_4472_4962_29877","label":"南郊区新旺乡新胜村卫生室","votes":"","isClick":true}]}