{"data":[{"id":"4430_4487_5124_32300","label":"凌井店乡卫生院","votes":"","isClick":true},{"id":"4430_4487_5124_32301","label":"凌井店乡河村卫生室","votes":"","isClick":true},{"id":"4430_4487_5124_32302","label":"凌井店乡湾里村卫生所","votes":"","isClick":true},{"id":"4430_4487_5124_32303","label":"凌井店乡安塘村卫生所","votes":"","isClick":true},{"id":"4430_4487_5124_32304","label":"凌井店乡西郭湫村卫生所","votes":"","isClick":true},{"id":"4430_4487_5124_32305","label":"凌井店乡西汉湖村卫生所","votes":"","isClick":true},{"id":"4430_4487_5124_32306","label":"凌井店乡大方山村卫生所","votes":"","isClick":true},{"id":"4430_4487_5124_32307","label":"凌井店乡西头村卫生所","votes":"","isClick":true},{"id":"4430_4487_5124_32308","label":"凌井店乡坡里村卫生所","votes":"","isClick":true},{"id":"4430_4487_5124_32309","label":"凌井店乡尧沟村卫生所","votes":"","isClick":true},{"id":"4430_4487_5124_32310","label":"凌井店乡东郭湫卫生所","votes":"","isClick":true},{"id":"4430_4487_5124_32311","label":"凌井店乡凌井店村卫生所","votes":"","isClick":true},{"id":"4430_4487_5124_32312","label":"凌井店乡蒿子坡村卫生所","votes":"","isClick":true},{"id":"4430_4487_5124_32313","label":"凌井店乡后街村卫生所","votes":"","isClick":true}]}