{"data":[{"id":"4430_4484_5103_31966","label":"太原市杏花岭区涧河社区卫生服务中心","votes":"","isClick":true},{"id":"4430_4484_5103_31967","label":"太原市杏花岭区七府园社区卫生服务站","votes":"","isClick":true},{"id":"4430_4484_5103_31968","label":"太原市杏花岭区柏杨树社区卫生服务站","votes":"","isClick":true},{"id":"4430_4484_5103_31969","label":"太原市杏花岭区同煦苑社区卫生服务站","votes":"","isClick":true},{"id":"4430_4484_5103_31970","label":"太原市杏花岭区白桦苑社区卫生服务站","votes":"","isClick":true},{"id":"4430_4484_5103_31971","label":"太原市杏花岭区耐火社区卫生服务站","votes":"","isClick":true},{"id":"4430_4484_5103_31972","label":"太原市杏花岭区锦绣苑社区卫生服务站","votes":"","isClick":true},{"id":"4430_4484_5103_31973","label":"太原市杏花岭区花南社区卫生服务站","votes":"","isClick":true}]}