{"data":[{"id":"4431_4492_5195_33896","label":"偏关县老营镇卫生院","votes":"","isClick":true},{"id":"4431_4492_5195_33897","label":"偏关县老营镇上土寨村卫生室","votes":"","isClick":true},{"id":"4431_4492_5195_33898","label":"偏关县老营镇窄沟村卫生室","votes":"","isClick":true},{"id":"4431_4492_5195_33899","label":"偏关县老营镇银子咀村卫生室","votes":"","isClick":true},{"id":"4431_4492_5195_33900","label":"偏关县老营镇鸭子坪村卫生室","votes":"","isClick":true},{"id":"4431_4492_5195_33901","label":"偏关县老营镇下土寨村卫生室","votes":"","isClick":true},{"id":"4431_4492_5195_33902","label":"偏关县老营镇西庄子村卫生室","votes":"","isClick":true},{"id":"4431_4492_5195_33903","label":"偏关县老营镇武家庄窝村卫生室","votes":"","isClick":true},{"id":"4431_4492_5195_33904","label":"偏关县老营镇史家圪台村卫生室","votes":"","isClick":true},{"id":"4431_4492_5195_33905","label":"偏关县老营镇木瓜贝村卫生室","votes":"","isClick":true},{"id":"4431_4492_5195_33906","label":"偏关县老营镇马肚梁村卫生室","votes":"","isClick":true},{"id":"4431_4492_5195_33907","label":"偏关县老营镇教儿埝村卫生室","votes":"","isClick":true},{"id":"4431_4492_5195_33908","label":"偏关县老营镇贾堡村卫生室","votes":"","isClick":true},{"id":"4431_4492_5195_33909","label":"偏关县老营镇冯家窑子村卫生室","votes":"","isClick":true},{"id":"4431_4492_5195_33910","label":"偏关县老营镇方城村卫生室","votes":"","isClick":true},{"id":"4431_4492_5195_33911","label":"偏关县老营镇大河湾村卫生室","votes":"","isClick":true},{"id":"4431_4492_5195_33912","label":"偏关县老营镇岩头寺村卫生室","votes":"","isClick":true},{"id":"4431_4492_5195_33913","label":"偏关县老营镇阴窝沟村卫生室","votes":"","isClick":true},{"id":"4431_4492_5195_33914","label":"偏关县老营镇段家沟村卫生室","votes":"","isClick":true}]}