{"data":[{"id":"4432_4507_5401_37622","label":"平遥县洪善中心卫生院","votes":"","isClick":true},{"id":"4432_4507_5401_37623","label":"平遥县洪善镇洪善村卫生室","votes":"","isClick":true},{"id":"4432_4507_5401_37624","label":"平遥县洪善镇新营村卫生室","votes":"","isClick":true},{"id":"4432_4507_5401_37625","label":"平遥县洪善镇南营村卫生室","votes":"","isClick":true},{"id":"4432_4507_5401_37626","label":"平遥县洪善镇白家庄村卫生室","votes":"","isClick":true},{"id":"4432_4507_5401_37627","label":"平遥县洪善镇兰村卫生室","votes":"","isClick":true},{"id":"4432_4507_5401_37628","label":"平遥县洪善镇北营村卫生室","votes":"","isClick":true},{"id":"4432_4507_5401_37629","label":"平遥县洪善镇东山湖村卫生室","votes":"","isClick":true},{"id":"4432_4507_5401_37630","label":"平遥县洪善镇南长寿村卫生室","votes":"","isClick":true},{"id":"4432_4507_5401_37631","label":"平遥县洪善镇北长寿村卫生室","votes":"","isClick":true},{"id":"4432_4507_5401_37632","label":"平遥县洪善镇郝村卫生室","votes":"","isClick":true},{"id":"4432_4507_5401_37633","label":"平遥县洪善镇宋家堡村卫生室","votes":"","isClick":true},{"id":"4432_4507_5401_37634","label":"平遥县洪善镇西山湖村卫生室","votes":"","isClick":true},{"id":"4432_4507_5401_37635","label":"平遥县洪善镇东堡村卫生室","votes":"","isClick":true},{"id":"4432_4507_5401_37636","label":"平遥县洪善中心卫生院沿村堡卫生站","votes":"","isClick":true},{"id":"4432_4507_5401_37637","label":"平遥县洪善镇五里庄村卫生室","votes":"","isClick":true},{"id":"4432_4507_5401_37638","label":"平遥县洪善镇沿村堡村卫生室","votes":"","isClick":true},{"id":"4432_4507_5401_37639","label":"平遥县洪善镇钦贤村卫生室","votes":"","isClick":true},{"id":"4432_4507_5401_37640","label":"平遥县洪善镇京陵村卫生室","votes":"","isClick":true},{"id":"4432_4507_5401_37641","label":"平遥县洪善镇东庄村卫生室","votes":"","isClick":true},{"id":"4432_4507_5401_37642","label":"平遥县洪善镇冀郭村卫生室","votes":"","isClick":true},{"id":"4432_4507_5401_37643","label":"平遥县洪善镇东大闫村卫生室","votes":"","isClick":true},{"id":"4432_4507_5401_37644","label":"平遥县洪善镇新胜村卫生室","votes":"","isClick":true},{"id":"4432_4507_5401_37645","label":"平遥县洪善镇尹村卫生室","votes":"","isClick":true},{"id":"4432_4507_5401_37646","label":"平遥县洪善镇小沿村卫生室","votes":"","isClick":true},{"id":"4432_4507_5401_37647","label":"平遥县洪善镇西大闫村卫生室","votes":"","isClick":true}]}