{"data":[{"id":"4434_4523_5604_42633","label":"朔州市朔城区南城街道办事处社区卫生服务中心","votes":"","isClick":true},{"id":"4434_4523_5604_42634","label":"朔州市朔城区南城街道办事处东关村卫生室","votes":"","isClick":true},{"id":"4434_4523_5604_42635","label":"朔州市朔城区南城街道办事处南街村卫生室","votes":"","isClick":true},{"id":"4434_4523_5604_42636","label":"朔州市朔城区南城街道办事处南关村卫生室","votes":"","isClick":true},{"id":"4434_4523_5604_42637","label":"朔州市朔城区南城街道办事处西街村卫生室","votes":"","isClick":true},{"id":"4434_4523_5604_42638","label":"北旺庄街道办事处社区卫生服务中心","votes":"","isClick":true},{"id":"4434_4523_5604_42639","label":"朔州市朔城区南城街道办事处东关街社区卫生服务站","votes":"","isClick":true},{"id":"4434_4523_5604_42640","label":"朔州市朔城区南城街道办事处城壕堰社区卫生服务站","votes":"","isClick":true},{"id":"4434_4523_5604_42641","label":"南城街道办事处长虹巷社区卫生服务站","votes":"","isClick":true},{"id":"4434_4523_5604_42642","label":"南城街道办事处水乡湾社区卫生服务站","votes":"","isClick":true},{"id":"4434_4523_5604_42643","label":"南城街道办事处东兴街社区卫生服务站","votes":"","isClick":true},{"id":"4434_4523_5604_42644","label":"南城街道办事处上地嘉园社区卫生服务站","votes":"","isClick":true},{"id":"4434_4523_5604_42645","label":"北旺庄街道办事处铁路社区卫生服务中心","votes":"","isClick":true},{"id":"4434_4523_5604_42646","label":"朔城区疾病预防控制中心","votes":"","isClick":true},{"id":"4434_4523_5604_42647","label":"朔州市朔城区南城街道办事处西山社区卫生服务站","votes":"","isClick":true},{"id":"4434_4523_5604_42648","label":"朔州市朔城区南城街道办事处开发南路社区卫生服务站","votes":"","isClick":true},{"id":"4434_4523_5604_42649","label":"朔州市朔城区南城街道办事处万象城社区卫生服务站","votes":"","isClick":true},{"id":"4434_4523_5604_42650","label":"朔州市朔城区妇幼保健计划生育服务中心","votes":"","isClick":true},{"id":"4434_4523_5604_42651","label":"朔州市朔城区卫生执法监督所","votes":"","isClick":true}]}