{"data":[{"id":"4435_4526_5648_43662","label":"垣曲县王茅镇中心卫生院","votes":"","isClick":true},{"id":"4435_4526_5648_43663","label":"垣曲县王茅镇柳庄村卫生室","votes":"","isClick":true},{"id":"4435_4526_5648_43664","label":"垣曲县王茅镇晁家坡村卫生室","votes":"","isClick":true},{"id":"4435_4526_5648_43665","label":"垣曲县王茅镇南坡村卫生室","votes":"","isClick":true},{"id":"4435_4526_5648_43666","label":"垣曲县王茅镇复兴村卫生室","votes":"","isClick":true},{"id":"4435_4526_5648_43667","label":"垣曲县王茅镇西王茅村卫生室","votes":"","isClick":true},{"id":"4435_4526_5648_43668","label":"垣曲县王茅镇王茅村卫生室","votes":"","isClick":true},{"id":"4435_4526_5648_43669","label":"垣曲县王茅镇东窑村卫生室","votes":"","isClick":true},{"id":"4435_4526_5648_43670","label":"垣曲县王茅镇小赵村卫生室","votes":"","isClick":true},{"id":"4435_4526_5648_43671","label":"垣曲县王茅镇寨里村卫生室","votes":"","isClick":true},{"id":"4435_4526_5648_43672","label":"垣曲县王茅镇上亳村卫生室","votes":"","isClick":true},{"id":"4435_4526_5648_43673","label":"垣曲县王茅镇下亳村卫生室","votes":"","isClick":true},{"id":"4435_4526_5648_43674","label":"垣曲县王茅镇白水村卫生室","votes":"","isClick":true},{"id":"4435_4526_5648_43675","label":"垣曲县王茅镇北河村卫生室","votes":"","isClick":true}]}