{"data":[{"id":"4435_4524_5619_42921","label":"万荣县王显卫生院","votes":"","isClick":true},{"id":"4435_4524_5619_42922","label":"万荣县王显乡张仪村卫生室","votes":"","isClick":true},{"id":"4435_4524_5619_42923","label":"万荣县王显乡东赵村卫生室","votes":"","isClick":true},{"id":"4435_4524_5619_42924","label":"万荣县王显乡东裴庄村卫生室","votes":"","isClick":true},{"id":"4435_4524_5619_42925","label":"万荣县王显乡兴王庄村卫生室","votes":"","isClick":true},{"id":"4435_4524_5619_42926","label":"万荣县王显乡程家庄村卫生室","votes":"","isClick":true},{"id":"4435_4524_5619_42927","label":"万荣县王显乡青谷庄村卫生室","votes":"","isClick":true},{"id":"4435_4524_5619_42928","label":"万荣县王显乡王显村卫生室","votes":"","isClick":true},{"id":"4435_4524_5619_42929","label":"万荣县王显乡贤胡村卫生室","votes":"","isClick":true},{"id":"4435_4524_5619_42930","label":"万荣县王显乡杨庄村卫生室","votes":"","isClick":true},{"id":"4435_4524_5619_42931","label":"万荣县王显乡许村卫生室","votes":"","isClick":true},{"id":"4435_4524_5619_42932","label":"万荣县王显乡偏店村卫生室","votes":"","isClick":true},{"id":"4435_4524_5619_42933","label":"万荣县王显乡吴庄村卫生室","votes":"","isClick":true},{"id":"4435_4524_5619_42934","label":"万荣县王显乡小谢村卫生室","votes":"","isClick":true},{"id":"4435_4524_5619_42935","label":"万荣县王显乡东和村卫生室","votes":"","isClick":true},{"id":"4435_4524_5619_42936","label":"万荣县王显乡东张村卫生室","votes":"","isClick":true},{"id":"4435_4524_5619_42937","label":"万荣县王显乡青谷村卫生室","votes":"","isClick":true},{"id":"4435_4524_5619_42938","label":"万荣县王显乡王正村卫生室","votes":"","isClick":true},{"id":"4435_4524_5619_42939","label":"万荣县王显乡竹家村卫生室","votes":"","isClick":true},{"id":"4435_4524_5619_42940","label":"万荣县王显乡东王村卫生室","votes":"","isClick":true},{"id":"4435_4524_5619_42941","label":"万荣县王显乡范家村卫生室","votes":"","isClick":true},{"id":"4435_4524_5619_42942","label":"万荣县王显乡年村卫生室","votes":"","isClick":true}]}