{"data":[{"id":"4435_4536_5751_46177","label":"五四一总医院中信运城医院","votes":"","isClick":true},{"id":"4435_4536_5751_46178","label":"际华三五三四制衣有限公司门诊部","votes":"","isClick":true},{"id":"4435_4536_5751_46179","label":"闻喜秋梅妇产医院","votes":"","isClick":true},{"id":"4435_4536_5751_46180","label":"闻喜县东镇中心卫生院","votes":"","isClick":true},{"id":"4435_4536_5751_46181","label":"闻喜县东镇新农村卫生室","votes":"","isClick":true},{"id":"4435_4536_5751_46182","label":"闻喜县东镇上白村卫生室","votes":"","isClick":true},{"id":"4435_4536_5751_46183","label":"闻喜县东镇西街村卫生室","votes":"","isClick":true},{"id":"4435_4536_5751_46184","label":"闻喜县东镇西干庆村卫生室","votes":"","isClick":true},{"id":"4435_4536_5751_46185","label":"闻喜县东镇东干庆村卫生室","votes":"","isClick":true},{"id":"4435_4536_5751_46186","label":"闻喜县东镇东白村卫生室","votes":"","isClick":true},{"id":"4435_4536_5751_46187","label":"闻喜县东镇三交村卫生室","votes":"","isClick":true},{"id":"4435_4536_5751_46188","label":"闻喜县东镇张家庄村卫生室","votes":"","isClick":true},{"id":"4435_4536_5751_46189","label":"闻喜县东镇小罗庄村卫生室","votes":"","isClick":true},{"id":"4435_4536_5751_46190","label":"闻喜县东镇下白村卫生室","votes":"","isClick":true},{"id":"4435_4536_5751_46191","label":"闻喜县东镇涑阳村卫生室","votes":"","isClick":true},{"id":"4435_4536_5751_46192","label":"闻喜县东镇上镇村卫生室","votes":"","isClick":true},{"id":"4435_4536_5751_46193","label":"闻喜县东镇西沟村卫生室","votes":"","isClick":true},{"id":"4435_4536_5751_46194","label":"闻喜县东镇东鲁村卫生室","votes":"","isClick":true},{"id":"4435_4536_5751_46195","label":"闻喜县东镇东镇村卫生室","votes":"","isClick":true},{"id":"4435_4536_5751_46196","label":"闻喜县东镇东姚村卫生室","votes":"","isClick":true},{"id":"4435_4536_5751_46197","label":"闻喜县东镇营里村卫生室","votes":"","isClick":true},{"id":"4435_4536_5751_46198","label":"闻喜县东镇仓底村卫生室","votes":"","isClick":true},{"id":"4435_4536_5751_46199","label":"闻喜县东镇中庄村卫生室","votes":"","isClick":true},{"id":"4435_4536_5751_46200","label":"闻喜县东镇官庄村卫生室","votes":"","isClick":true},{"id":"4435_4536_5751_46201","label":"闻喜县东镇大罗庄村卫生室","votes":"","isClick":true},{"id":"4435_4536_5751_46202","label":"闻喜县东镇裴村卫生室","votes":"","isClick":true},{"id":"4435_4536_5751_46203","label":"闻喜县东镇西姚村卫生室","votes":"","isClick":true},{"id":"4435_4536_5751_46204","label":"闻喜县东镇川口村卫生室","votes":"","isClick":true},{"id":"4435_4536_5751_46205","label":"闻喜县东镇党家庄村卫生室","votes":"","isClick":true}]}