{"data":[{"id":"4436_4538_5784_47189","label":"壶关县鹅屋乡卫生院","votes":"","isClick":true},{"id":"4436_4538_5784_47190","label":"长治市壶关县鹅屋乡东壶陵水村卫生所","votes":"","isClick":true},{"id":"4436_4538_5784_47191","label":"长治市壶关县鹅屋乡东土池村卫生所","votes":"","isClick":true},{"id":"4436_4538_5784_47192","label":"长治市壶关县鹅屋乡鹅屋村卫生所","votes":"","isClick":true},{"id":"4436_4538_5784_47193","label":"长治市壶关县鹅屋乡恶石掌村卫生所","votes":"","isClick":true},{"id":"4436_4538_5784_47194","label":"长治市壶关县鹅屋乡红脑上村卫生所","votes":"","isClick":true},{"id":"4436_4538_5784_47195","label":"长治市壶关县鹅屋乡黄崖底村卫生所","votes":"","isClick":true},{"id":"4436_4538_5784_47196","label":"长治市壶关县鹅屋乡黄崖头村卫生所","votes":"","isClick":true},{"id":"4436_4538_5784_47197","label":"长治市壶关县鹅屋乡或岭西村卫生所","votes":"","isClick":true},{"id":"4436_4538_5784_47198","label":"长治市壶关县鹅屋乡南倒寺村卫生所","votes":"","isClick":true},{"id":"4436_4538_5784_47199","label":"长治市壶关县鹅屋乡柳泉村卫生所","votes":"","isClick":true},{"id":"4436_4538_5784_47200","label":"长治市壶关县鹅屋乡牛洞上村卫生所","votes":"","isClick":true},{"id":"4436_4538_5784_47201","label":"长治市壶关县鹅屋乡沙岗沟村卫生所","votes":"","isClick":true},{"id":"4436_4538_5784_47202","label":"长治市壶关县鹅屋乡师家背村卫生所","votes":"","isClick":true},{"id":"4436_4538_5784_47203","label":"长治市壶关县鹅屋乡石圪爽村卫生所","votes":"","isClick":true},{"id":"4436_4538_5784_47204","label":"长治市壶关县鹅屋乡五里沟村卫生所","votes":"","isClick":true},{"id":"4436_4538_5784_47205","label":"长治市壶关县鹅屋乡西壶陵水村卫生所","votes":"","isClick":true},{"id":"4436_4538_5784_47206","label":"长治市壶关县鹅屋乡西土池村卫生所","votes":"","isClick":true},{"id":"4436_4538_5784_47207","label":"长治市壶关县鹅屋乡阴山坝村卫生所","votes":"","isClick":true},{"id":"4436_4538_5784_47208","label":"长治市壶关县鹅屋乡黄崖底村诊所","votes":"","isClick":true}]}