{"data":[{"id":"4437_4552_5949_50945","label":"沙坪社区卫生服务中心","votes":"","isClick":true},{"id":"4437_4552_5949_50946","label":"沙沟社区卫生服务站","votes":"","isClick":true},{"id":"4437_4552_5949_50947","label":"黄石板社区卫生服务站","votes":"","isClick":true},{"id":"4437_4552_5949_50948","label":"郊区平坦镇前庄村卫生所","votes":"","isClick":true},{"id":"4437_4552_5949_50949","label":"北头咀村卫生所","votes":"","isClick":true},{"id":"4437_4552_5949_50950","label":"老平掌村卫生所","votes":"","isClick":true},{"id":"4437_4552_5949_50951","label":"庙上村卫生所","votes":"","isClick":true},{"id":"4437_4552_5949_50952","label":"大村卫生所","votes":"","isClick":true},{"id":"4437_4552_5949_50953","label":"半坡村卫生所","votes":"","isClick":true}]}