{"data":[{"id":"4_37_7788","label":"潞华办事处社区卫生服务中心","votes":"","isClick":true},{"id":"4_37_7789","label":"潞华办白鹤观卫生所","votes":"","isClick":true},{"id":"4_37_7790","label":"潞华办三管阁卫生所","votes":"","isClick":true},{"id":"4_37_7791","label":"潞华办瓦窑头社区卫生所","votes":"","isClick":true},{"id":"4_37_7792","label":"潞华办瓦窑头第二卫生所","votes":"","isClick":true},{"id":"4_37_7793","label":"潞华办辛庄卫生所","votes":"","isClick":true},{"id":"4_37_7794","label":"潞华办岭后卫生所","votes":"","isClick":true},{"id":"4_37_7795","label":"潞华办五里后卫生所","votes":"","isClick":true},{"id":"4_37_7796","label":"潞华办王山坪卫生所","votes":"","isClick":true},{"id":"4_37_7797","label":"潞华办白鹤观第三卫生所","votes":"","isClick":true},{"id":"4_37_7798","label":"潞华办东南山社区卫生所","votes":"","isClick":true},{"id":"4_37_7799","label":"潞华办史坊村卫生所","votes":"","isClick":true},{"id":"4_37_7800","label":"潞华办南街社区卫生所","votes":"","isClick":true},{"id":"4_37_7801","label":"潞华办南关社区卫生所","votes":"","isClick":true},{"id":"4_37_7802","label":"潞华办北街社区卫生所","votes":"","isClick":true},{"id":"4_37_7803","label":"潞华办南庄村卫生所","votes":"","isClick":true},{"id":"4_37_7804","label":"潞华办古南关社区卫生所","votes":"","isClick":true},{"id":"4_37_7805","label":"潞华办古南关社区第二卫生所","votes":"","isClick":true},{"id":"4_37_7806","label":"潞华办西南山社区卫生所","votes":"","isClick":true},{"id":"4_37_7807","label":"潞华办侯家庄村卫生所","votes":"","isClick":true},{"id":"4_37_7808","label":"潞华办东贾村卫生所","votes":"","isClick":true},{"id":"4_37_7809","label":"潞华办西贾村卫生所","votes":"","isClick":true},{"id":"4_37_7810","label":"潞华办西贾村第二卫生所","votes":"","isClick":true},{"id":"4_37_7811","label":"潞华办西贾村第三卫生所","votes":"","isClick":true},{"id":"4_37_7812","label":"潞华办东街社区卫生所","votes":"","isClick":true},{"id":"4_37_7813","label":"潞华办东街社区第二卫生所","votes":"","isClick":true},{"id":"4_37_7814","label":"潞华办山底村卫生所","votes":"","isClick":true},{"id":"4_37_7815","label":"潞华办山底村第二卫生所","votes":"","isClick":true},{"id":"4_37_7816","label":"潞华办西村第二卫生所","votes":"","isClick":true},{"id":"4_37_7817","label":"潞华办西村第三卫生所","votes":"","isClick":true},{"id":"4_37_7818","label":"潞华办西街社区卫生所","votes":"","isClick":true},{"id":"4_37_7819","label":"潞华办西街第三社区卫生所","votes":"","isClick":true},{"id":"4_37_7820","label":"潞华办西村卫生所","votes":"","isClick":true},{"id":"4_37_7821","label":"潞华办北庄村卫生所","votes":"","isClick":true},{"id":"4_37_7822","label":"潞华办西街社区第二卫生所","votes":"","isClick":true},{"id":"4_37_7823","label":"潞城区水岸春城社区卫生服务站","votes":"","isClick":true},{"id":"4_37_7824","label":"成家川办事处社区卫生服务中心","votes":"","isClick":true},{"id":"4_37_7825","label":"潞城市成家川办事处峪北村卫生所","votes":"","isClick":true},{"id":"4_37_7826","label":"潞城市成家川办事处驮坡村卫生所","votes":"","isClick":true},{"id":"4_37_7827","label":"潞城市成家川办事处米家村卫生所","votes":"","isClick":true},{"id":"4_37_7828","label":"潞城市成家川办事处后峧村卫生所","votes":"","isClick":true},{"id":"4_37_7829","label":"潞城市成家川办事处南村村卫生所","votes":"","isClick":true},{"id":"4_37_7830","label":"潞城市成家川办事处郭家庄村卫生所","votes":"","isClick":true},{"id":"4_37_7831","label":"潞城市成家川办事处黄池村卫生所","votes":"","isClick":true},{"id":"4_37_7832","label":"潞城市成家川办事处苗家村卫生所","votes":"","isClick":true},{"id":"4_37_7833","label":"潞城市成家川办事处成家川村卫生所","votes":"","isClick":true},{"id":"4_37_7834","label":"潞城市成家川办事处成家村卫生所","votes":"","isClick":true},{"id":"4_37_7835","label":"潞城市成家川办事处鼎留村卫生所","votes":"","isClick":true},{"id":"4_37_7836","label":"潞城市成家川办事处东邑村卫生所","votes":"","isClick":true},{"id":"4_37_7837","label":"潞城市成家川办事处下社村卫生所","votes":"","isClick":true},{"id":"4_37_7838","label":"潞城市成家川办事处李家村卫生所","votes":"","isClick":true},{"id":"4_37_7839","label":"潞城市成家川办事处沟北村卫生所","votes":"","isClick":true},{"id":"4_37_7840","label":"潞城市成家川办事处申家村卫生所","votes":"","isClick":true},{"id":"4_37_7841","label":"潞城市成家川办事处沟东村卫生所","votes":"","isClick":true},{"id":"4_37_7842","label":"潞城市成家川办事处窑上村卫生所","votes":"","isClick":true},{"id":"4_37_7843","label":"潞城市成家川办事处大桥村卫生所","votes":"","isClick":true},{"id":"4_37_7844","label":"潞城市成家川办事处河西村卫生所","votes":"","isClick":true},{"id":"4_37_7845","label":"潞城市成家川办事处王家村卫生所","votes":"","isClick":true},{"id":"4_37_7846","label":"潞城市成家川办事处西山村卫生所","votes":"","isClick":true},{"id":"4_37_7847","label":"潞城市成家川办事处神泉村卫生所","votes":"","isClick":true},{"id":"4_37_7848","label":"潞城市成家川办事处祥井村卫生所","votes":"","isClick":true},{"id":"4_37_7849","label":"潞城市成家川办事处三井村卫生所","votes":"","isClick":true},{"id":"4_37_7850","label":"潞城市成家川办事处台东村卫生所","votes":"","isClick":true},{"id":"4_37_7851","label":"店上镇卫生院","votes":"","isClick":true},{"id":"4_37_7852","label":"潞城市店上镇常庄村卫生所","votes":"","isClick":true},{"id":"4_37_7853","label":"潞城市店上镇李家庄村卫生所","votes":"","isClick":true},{"id":"4_37_7854","label":"店上镇申庄第二卫生所","votes":"","isClick":true},{"id":"4_37_7855","label":"潞城市店上镇温村卫生所","votes":"","isClick":true},{"id":"4_37_7856","label":"店上镇邱壁卫生所","votes":"","isClick":true},{"id":"4_37_7857","label":"店上镇柳江沟村卫生所","votes":"","isClick":true},{"id":"4_37_7858","label":"店上镇韩村卫生所","votes":"","isClick":true},{"id":"4_37_7859","label":"店上镇北村第二卫生所","votes":"","isClick":true},{"id":"4_37_7860","label":"店上镇牛村卫生所","votes":"","isClick":true},{"id":"4_37_7861","label":"店上镇宋村第三卫生所","votes":"","isClick":true},{"id":"4_37_7862","label":"店上镇赤头卫生所","votes":"","isClick":true},{"id":"4_37_7863","label":"店上镇下栗卫生所","votes":"","isClick":true},{"id":"4_37_7864","label":"店上镇宋村卫生所","votes":"","isClick":true},{"id":"4_37_7865","label":"店上镇枣臻村第二卫生所","votes":"","isClick":true},{"id":"4_37_7866","label":"店上镇上栗卫生所","votes":"","isClick":true},{"id":"4_37_7867","label":"店上镇曹沟村卫生所","votes":"","isClick":true},{"id":"4_37_7868","label":"店上镇店上村第二卫生所","votes":"","isClick":true},{"id":"4_37_7869","label":"店上镇河湃村第三卫生所","votes":"","isClick":true},{"id":"4_37_7870","label":"店上镇黄沙岭村卫生所","votes":"","isClick":true},{"id":"4_37_7871","label":"店上镇马江沟村卫生所","votes":"","isClick":true},{"id":"4_37_7872","label":"店上镇周武村第二卫生所","votes":"","isClick":true},{"id":"4_37_7873","label":"潞城市史回乡卫生院","votes":"","isClick":true},{"id":"4_37_7874","label":"潞城市史回乡山口村卫生所","votes":"","isClick":true},{"id":"4_37_7875","label":"潞城市史回乡垂阳村第二卫生所","votes":"","isClick":true},{"id":"4_37_7876","label":"潞城市史回乡垂阳村第三卫生所","votes":"","isClick":true},{"id":"4_37_7877","label":"潞城市史回乡郭家堡村卫生所","votes":"","isClick":true},{"id":"4_37_7878","label":"潞城市史回乡宋家庄村卫生所","votes":"","isClick":true},{"id":"4_37_7879","label":"潞城市史回乡朱家川村卫生所","votes":"","isClick":true},{"id":"4_37_7880","label":"潞城市史回乡朱家川村第二卫生所","votes":"","isClick":true},{"id":"4_37_7881","label":"潞城市史回乡梨树凹村卫生所","votes":"","isClick":true},{"id":"4_37_7882","label":"潞城市史回乡山脑村","votes":"","isClick":true},{"id":"4_37_7883","label":"潞城市史回乡楼后村卫生所","votes":"","isClick":true},{"id":"4_37_7884","label":"潞城市史回乡向阳坡村卫生所","votes":"","isClick":true},{"id":"4_37_7885","label":"潞城市史回乡曲里村卫生所","votes":"","isClick":true},{"id":"4_37_7886","label":"潞城市史回乡王里堡村卫生所","votes":"","isClick":true},{"id":"4_37_7887","label":"潞城市史回乡黄漳村卫生所","votes":"","isClick":true},{"id":"4_37_7888","label":"潞城市史回乡马池沟村卫生所","votes":"","isClick":true},{"id":"4_37_7889","label":"潞城市史回乡任和村卫生所","votes":"","isClick":true},{"id":"4_37_7890","label":"潞城市史回乡小常村卫生所","votes":"","isClick":true},{"id":"4_37_7891","label":"潞城市史回乡大常村卫生所","votes":"","isClick":true},{"id":"4_37_7892","label":"潞城市史回乡白家沟村卫生所","votes":"","isClick":true},{"id":"4_37_7893","label":"潞城市史回乡桥沟村卫生所","votes":"","isClick":true},{"id":"4_37_7894","label":"潞城市史回乡小沟村","votes":"","isClick":true},{"id":"4_37_7895","label":"潞城市史回乡闫李庄村卫生室","votes":"","isClick":true},{"id":"4_37_7896","label":"潞城市史回乡李家沟村卫生所","votes":"","isClick":true},{"id":"4_37_7897","label":"翟店镇卫生院","votes":"","isClick":true},{"id":"4_37_7898","label":"潞城市翟店镇郭村卫生所","votes":"","isClick":true},{"id":"4_37_7899","label":"潞城市翟店镇南天贡村卫生所","votes":"","isClick":true},{"id":"4_37_7900","label":"潞城市翟店镇北舍卫生所","votes":"","isClick":true},{"id":"4_37_7901","label":"潞城市翟店镇东天贡村卫生所","votes":"","isClick":true},{"id":"4_37_7902","label":"潞城市翟店镇南舍村卫生所","votes":"","isClick":true},{"id":"4_37_7903","label":"潞城市翟店镇寨上村卫生所","votes":"","isClick":true},{"id":"4_37_7904","label":"潞城市翟店镇小天贡村卫生所","votes":"","isClick":true},{"id":"4_37_7905","label":"潞城市翟店镇贾村第二卫生所","votes":"","isClick":true},{"id":"4_37_7906","label":"潞城市翟店镇翟店村卫生所","votes":"","isClick":true},{"id":"4_37_7907","label":"潞城市翟店镇崇道村卫生所","votes":"","isClick":true},{"id":"4_37_7908","label":"潞城市翟店镇羌城村卫生所","votes":"","isClick":true},{"id":"4_37_7909","label":"潞城市翟店镇西天贡村卫生所","votes":"","isClick":true},{"id":"4_37_7910","label":"合室乡卫生院","votes":"","isClick":true},{"id":"4_37_7911","label":"合室乡河后村卫生所","votes":"","isClick":true},{"id":"4_37_7912","label":"合室乡儒教村卫生所","votes":"","isClick":true},{"id":"4_37_7913","label":"合室乡余庄村卫生所","votes":"","isClick":true},{"id":"4_37_7914","label":"合室乡熬脑村卫生所","votes":"","isClick":true},{"id":"4_37_7915","label":"合室乡中村卫生所","votes":"","isClick":true},{"id":"4_37_7916","label":"合室乡张家河村卫生所","votes":"","isClick":true},{"id":"4_37_7917","label":"合室乡姜庄村卫生所","votes":"","isClick":true},{"id":"4_37_7918","label":"合室乡东山村卫生所","votes":"","isClick":true},{"id":"4_37_7919","label":"合室乡堡头村卫生所","votes":"","isClick":true},{"id":"4_37_7920","label":"合室乡阳坡村卫生所","votes":"","isClick":true},{"id":"4_37_7921","label":"合室乡赤疙倒村卫生所","votes":"","isClick":true},{"id":"4_37_7922","label":"合室乡桥堡村卫生所","votes":"","isClick":true},{"id":"4_37_7923","label":"合室乡西岭村卫生所","votes":"","isClick":true},{"id":"4_37_7924","label":"合室乡沟溃村卫生所","votes":"","isClick":true},{"id":"4_37_7925","label":"合室乡王郭庄村卫生所","votes":"","isClick":true},{"id":"4_37_7926","label":"合室乡北行村卫生所","votes":"","isClick":true},{"id":"4_37_7927","label":"合室乡北山后村卫生所","votes":"","isClick":true},{"id":"4_37_7928","label":"合室乡西坡村卫生所","votes":"","isClick":true},{"id":"4_37_7929","label":"合室乡合室村卫生所","votes":"","isClick":true},{"id":"4_37_7930","label":"微子镇卫生院","votes":"","isClick":true},{"id":"4_37_7931","label":"微子镇后河村卫生所","votes":"","isClick":true},{"id":"4_37_7932","label":"微子镇西靳村卫生所","votes":"","isClick":true},{"id":"4_37_7933","label":"微子镇称沟湾村卫生所","votes":"","isClick":true},{"id":"4_37_7934","label":"微子镇东靳村卫生所","votes":"","isClick":true},{"id":"4_37_7935","label":"微子镇沟东村卫生所","votes":"","isClick":true},{"id":"4_37_7936","label":"微子镇韩家园村卫生所","votes":"","isClick":true},{"id":"4_37_7937","label":"微子镇洪漳村卫生所","votes":"","isClick":true},{"id":"4_37_7938","label":"微子镇小辽河村卫生所","votes":"","isClick":true},{"id":"4_37_7939","label":"微子镇郝家沟村卫生所","votes":"","isClick":true},{"id":"4_37_7940","label":"微子镇魏家庄村卫生所","votes":"","isClick":true},{"id":"4_37_7941","label":"微子镇漫流河村卫生所","votes":"","isClick":true},{"id":"4_37_7942","label":"微子镇子北村卫生所","votes":"","isClick":true},{"id":"4_37_7943","label":"微子镇王家庄村卫生所","votes":"","isClick":true},{"id":"4_37_7944","label":"微子镇冯村卫生所","votes":"","isClick":true},{"id":"4_37_7945","label":"微子镇花园村卫生所","votes":"","isClick":true},{"id":"4_37_7946","label":"微子镇薛家庄村卫生所","votes":"","isClick":true},{"id":"4_37_7947","label":"微子镇子南村第二卫生所","votes":"","isClick":true},{"id":"4_37_7948","label":"微子镇和合村卫生所","votes":"","isClick":true},{"id":"4_37_7949","label":"微子镇李家庄村卫生所","votes":"","isClick":true},{"id":"4_37_7950","label":"微子镇王都庄村卫生所","votes":"","isClick":true},{"id":"4_37_7951","label":"微子镇石匣村卫生所","votes":"","isClick":true},{"id":"4_37_7952","label":"微子镇辛庄村卫生所","votes":"","isClick":true},{"id":"4_37_7953","label":"微子镇秦家山村卫生所","votes":"","isClick":true},{"id":"4_37_7954","label":"微子镇神头村第二卫生所","votes":"","isClick":true},{"id":"4_37_7955","label":"微子镇漫流岭村卫生所","votes":"","isClick":true},{"id":"4_37_7956","label":"黄牛蹄乡卫生院","votes":"","isClick":true},{"id":"4_37_7957","label":"黄牛蹄村卫生所","votes":"","isClick":true},{"id":"4_37_7958","label":"南桃村卫生所","votes":"","isClick":true},{"id":"4_37_7959","label":"南桃村第二卫生所","votes":"","isClick":true},{"id":"4_37_7960","label":"庄头村卫生所","votes":"","isClick":true},{"id":"4_37_7961","label":"盘石头村卫生所","votes":"","isClick":true},{"id":"4_37_7962","label":"青口村卫生所","votes":"","isClick":true},{"id":"4_37_7963","label":"南庄村卫生所","votes":"","isClick":true},{"id":"4_37_7964","label":"下河村卫生所","votes":"","isClick":true},{"id":"4_37_7965","label":"岭后村卫生所","votes":"","isClick":true},{"id":"4_37_7966","label":"辛安村卫生所","votes":"","isClick":true},{"id":"4_37_7967","label":"南华辿村卫生所","votes":"","isClick":true},{"id":"4_37_7968","label":"辽河头村卫生所","votes":"","isClick":true},{"id":"4_37_7969","label":"上黄村卫生所","votes":"","isClick":true},{"id":"4_37_7970","label":"下黄村卫生所","votes":"","isClick":true},{"id":"4_37_7971","label":"安岭寺卫生所","votes":"","isClick":true},{"id":"4_37_7972","label":"辽河村卫生所","votes":"","isClick":true},{"id":"4_37_7973","label":"李庄村第一卫生所","votes":"","isClick":true},{"id":"4_37_7974","label":"李庄村第二卫生所","votes":"","isClick":true},{"id":"4_37_7975","label":"李庄村第三卫生所","votes":"","isClick":true},{"id":"4_37_7976","label":"王家庄村卫生所","votes":"","isClick":true},{"id":"4_37_7977","label":"辛安泉卫生院","votes":"","isClick":true},{"id":"4_37_7978","label":"潞城市辛安泉镇西北卫生所","votes":"","isClick":true},{"id":"4_37_7979","label":"辛安泉镇石梁村卫生所","votes":"","isClick":true},{"id":"4_37_7980","label":"潞城市辛安泉南马村卫生所","votes":"","isClick":true},{"id":"4_37_7981","label":"潞城市辛安泉镇南马庄村卫生所","votes":"","isClick":true},{"id":"4_37_7982","label":"潞城市辛安泉镇曹庄村卫生所","votes":"","isClick":true},{"id":"4_37_7983","label":"潞城市辛安泉镇井峪村卫生所","votes":"","isClick":true},{"id":"4_37_7984","label":"潞城市辛安泉镇上村卫生所","votes":"","isClick":true},{"id":"4_37_7985","label":"潞城市辛安泉镇常村卫生所","votes":"","isClick":true},{"id":"4_37_7986","label":"潞城市辛安泉镇续村卫生所","votes":"","isClick":true},{"id":"4_37_7987","label":"潞城市辛安泉镇申家山村卫生所","votes":"","isClick":true},{"id":"4_37_7988","label":"潞城市辛安泉镇潞河村第二卫生所","votes":"","isClick":true},{"id":"4_37_7989","label":"潞城市辛安泉镇茶棚村卫生所","votes":"","isClick":true},{"id":"4_37_7990","label":"潞城市辛安泉镇古城村","votes":"","isClick":true},{"id":"4_37_7991","label":"潞城市辛安泉镇南流村卫生所","votes":"","isClick":true},{"id":"4_37_7992","label":"潞城市辛安泉镇西南村","votes":"","isClick":true},{"id":"4_37_7993","label":"潞城市辛安泉镇斜底村卫生所","votes":"","isClick":true},{"id":"4_37_7994","label":"潞城市辛安泉镇涧口村第一卫生所","votes":"","isClick":true},{"id":"4_37_7995","label":"潞城市辛安泉镇涧口村第二卫生所","votes":"","isClick":true},{"id":"4_37_7996","label":"辛安泉镇安乐卫生所","votes":"","isClick":true},{"id":"4_37_7997","label":"天脊社区卫生服务站","votes":"","isClick":true},{"id":"4_37_7998","label":"晋水社区卫生服务站","votes":"","isClick":true},{"id":"4_37_7999","label":"西华北路社区卫生服务站","votes":"","isClick":true},{"id":"4_37_8000","label":"潞康社区卫生服务站","votes":"","isClick":true},{"id":"4_37_8001","label":"学府街社区卫生服务站","votes":"","isClick":true},{"id":"4_37_8002","label":"城南社区卫生服务站","votes":"","isClick":true},{"id":"4_37_8003","label":"潞城市疾病预防控制中心","votes":"","isClick":true},{"id":"4_37_8004","label":"潞城市妇幼保健计划生育服务中心","votes":"","isClick":true},{"id":"4_37_8005","label":"潞城市人民医院","votes":"","isClick":true},{"id":"4_37_8006","label":"潞城协和医院","votes":"","isClick":true}]}