{"data":[{"id":"7_58_13743","label":"平遥县城西社区卫生服务中心","votes":"","isClick":true},{"id":"7_58_13744","label":"平遥县古陶镇卫生院","votes":"","isClick":true},{"id":"7_58_13745","label":"平遥县古陶镇东城村卫生室","votes":"","isClick":true},{"id":"7_58_13746","label":"平遥县古陶镇南城村卫生室","votes":"","isClick":true},{"id":"7_58_13747","label":"平遥县古陶镇干坑村卫生室","votes":"","isClick":true},{"id":"7_58_13748","label":"平遥县古陶镇闫壁村卫生室","votes":"","isClick":true},{"id":"7_58_13749","label":"平遥县古陶镇北城村卫生室","votes":"","isClick":true},{"id":"7_58_13750","label":"平遥县古陶镇十九街村卫生室","votes":"","isClick":true},{"id":"7_58_13751","label":"平遥县古陶镇城南堡村卫生室","votes":"","isClick":true},{"id":"7_58_13752","label":"平遥县古陶镇新南堡村卫生室","votes":"","isClick":true},{"id":"7_58_13753","label":"平遥县古陶镇西城村卫生室","votes":"","isClick":true},{"id":"7_58_13754","label":"平遥县古陶镇新庄村卫生室","votes":"","isClick":true},{"id":"7_58_13755","label":"平遥县古陶镇东城村学府街卫生室","votes":"","isClick":true},{"id":"7_58_13756","label":"平遥县洪善中心卫生院","votes":"","isClick":true},{"id":"7_58_13757","label":"平遥县洪善镇洪善村卫生室","votes":"","isClick":true},{"id":"7_58_13758","label":"平遥县洪善镇新营村卫生室","votes":"","isClick":true},{"id":"7_58_13759","label":"平遥县洪善镇南营村卫生室","votes":"","isClick":true},{"id":"7_58_13760","label":"平遥县洪善镇白家庄村卫生室","votes":"","isClick":true},{"id":"7_58_13761","label":"平遥县洪善镇兰村卫生室","votes":"","isClick":true},{"id":"7_58_13762","label":"平遥县洪善镇北营村卫生室","votes":"","isClick":true},{"id":"7_58_13763","label":"平遥县洪善镇东山湖村卫生室","votes":"","isClick":true},{"id":"7_58_13764","label":"平遥县洪善镇南长寿村卫生室","votes":"","isClick":true},{"id":"7_58_13765","label":"平遥县洪善镇北长寿村卫生室","votes":"","isClick":true},{"id":"7_58_13766","label":"平遥县洪善镇郝村卫生室","votes":"","isClick":true},{"id":"7_58_13767","label":"平遥县洪善镇宋家堡村卫生室","votes":"","isClick":true},{"id":"7_58_13768","label":"平遥县洪善镇西山湖村卫生室","votes":"","isClick":true},{"id":"7_58_13769","label":"平遥县洪善镇东堡村卫生室","votes":"","isClick":true},{"id":"7_58_13770","label":"平遥县宁固中心卫生院","votes":"","isClick":true},{"id":"7_58_13771","label":"平遥县宁固镇宁固村卫生室","votes":"","isClick":true},{"id":"7_58_13772","label":"平遥县宁固镇滩头村卫生室","votes":"","isClick":true},{"id":"7_58_13773","label":"平遥县宁固镇左家堡村卫生室","votes":"","isClick":true},{"id":"7_58_13774","label":"平遥县宁固镇西张赵村卫生室","votes":"","isClick":true},{"id":"7_58_13775","label":"平遥县宁固镇南堡村卫生室","votes":"","isClick":true},{"id":"7_58_13776","label":"平遥县宁固镇河西村卫生室","votes":"","isClick":true},{"id":"7_58_13777","label":"平遥县宁固镇任家堡村卫生室","votes":"","isClick":true},{"id":"7_58_13778","label":"平遥县宁固镇东张赵村卫生室","votes":"","isClick":true},{"id":"7_58_13779","label":"平遥县宁固镇梁家堡村卫生室","votes":"","isClick":true},{"id":"7_58_13780","label":"平遥县宁固镇北侯村卫生室","votes":"","isClick":true},{"id":"7_58_13781","label":"平遥县宁固镇南侯村卫生室","votes":"","isClick":true},{"id":"7_58_13782","label":"平遥县南政乡卫生院","votes":"","isClick":true},{"id":"7_58_13783","label":"平遥县南政乡闫家庄村卫生室","votes":"","isClick":true},{"id":"7_58_13784","label":"平遥县南政乡西刘村卫生室","votes":"","isClick":true},{"id":"7_58_13785","label":"平遥县南政乡小刘村卫生室","votes":"","isClick":true},{"id":"7_58_13786","label":"平遥县南政乡娃留村卫生室","votes":"","isClick":true},{"id":"7_58_13787","label":"平遥县南政乡侯郭村卫生室","votes":"","isClick":true},{"id":"7_58_13788","label":"平遥县南政乡东刘村卫生室","votes":"","isClick":true},{"id":"7_58_13789","label":"平遥县南政乡里村卫生室","votes":"","isClick":true},{"id":"7_58_13790","label":"平遥县南政乡南北庄村卫生室","votes":"","isClick":true},{"id":"7_58_13791","label":"平遥县南政乡南政村卫生室","votes":"","isClick":true},{"id":"7_58_13792","label":"平遥县岳壁乡卫生院","votes":"","isClick":true},{"id":"7_58_13793","label":"平遥县岳壁乡西源祠村卫生室","votes":"","isClick":true},{"id":"7_58_13794","label":"平遥县岳壁乡黎基村卫生室","votes":"","isClick":true},{"id":"7_58_13795","label":"平遥县岳壁乡梁村卫生室","votes":"","isClick":true},{"id":"7_58_13796","label":"平遥县岳壁乡岳南村卫生室","votes":"","isClick":true},{"id":"7_58_13797","label":"平遥县岳壁乡岳中村卫生室","votes":"","isClick":true},{"id":"7_58_13798","label":"平遥县岳壁乡岳北村卫生室","votes":"","isClick":true},{"id":"7_58_13799","label":"平遥县岳壁乡尹回村卫生室","votes":"","isClick":true},{"id":"7_58_13800","label":"平遥县岳壁乡小城村卫生室","votes":"","isClick":true},{"id":"7_58_13801","label":"平遥县岳壁乡西郭村卫生室","votes":"","isClick":true},{"id":"7_58_13802","label":"平遥县岳壁乡东郭村卫生室","votes":"","isClick":true},{"id":"7_58_13803","label":"平遥县岳壁乡金庄村卫生室","votes":"","isClick":true},{"id":"7_58_13804","label":"平遥县岳壁乡闫良村卫生室","votes":"","isClick":true},{"id":"7_58_13805","label":"平遥县岳壁乡高林村卫生室","votes":"","isClick":true},{"id":"7_58_13806","label":"平遥县朱坑中心卫生院","votes":"","isClick":true},{"id":"7_58_13807","label":"平遥县朱坑乡朱坑村卫生室","votes":"","isClick":true},{"id":"7_58_13808","label":"平遥县朱坑乡汪湛村卫生室","votes":"","isClick":true},{"id":"7_58_13809","label":"平遥县朱坑乡庞庄村卫生室","votes":"","isClick":true},{"id":"7_58_13810","label":"平遥县朱坑乡洪南村卫生室","votes":"","isClick":true},{"id":"7_58_13811","label":"平遥县朱坑乡龙跃村卫生室","votes":"","isClick":true},{"id":"7_58_13812","label":"平遥县朱坑乡兴东村卫生室","votes":"","isClick":true},{"id":"7_58_13813","label":"平遥县朱坑乡庄则村卫生室","votes":"","isClick":true},{"id":"7_58_13814","label":"平遥县朱坑乡南依涧村卫生室","votes":"","isClick":true},{"id":"7_58_13815","label":"平遥县朱坑乡北依涧村卫生室","votes":"","isClick":true},{"id":"7_58_13816","label":"平遥县朱坑乡东岩窑村卫生室","votes":"","isClick":true},{"id":"7_58_13817","label":"平遥县朱坑乡山坡头村卫生室","votes":"","isClick":true},{"id":"7_58_13818","label":"平遥县朱坑乡侯家庄村卫生室","votes":"","isClick":true},{"id":"7_58_13819","label":"平遥县朱坑乡贾家坡村卫生室","votes":"","isClick":true},{"id":"7_58_13820","label":"平遥县朱坑乡张家庄村卫生室","votes":"","isClick":true},{"id":"7_58_13821","label":"平遥县朱坑乡雷家庄村卫生室","votes":"","isClick":true},{"id":"7_58_13822","label":"平遥县朱坑乡苏家庄村卫生室","votes":"","isClick":true},{"id":"7_58_13823","label":"平遥县香乐乡卫生院","votes":"","isClick":true},{"id":"7_58_13824","label":"平遥县香乐乡赵坦村卫生室","votes":"","isClick":true},{"id":"7_58_13825","label":"平遥县香乐乡青落村卫生室","votes":"","isClick":true},{"id":"7_58_13826","label":"平遥县香乐乡安固村卫生室","votes":"","isClick":true},{"id":"7_58_13827","label":"平遥县香乐乡武坊村卫生室","votes":"","isClick":true},{"id":"7_58_13828","label":"平遥县香乐乡云家庄村卫生室","votes":"","isClick":true},{"id":"7_58_13829","label":"平遥县香乐乡郝庄村卫生室","votes":"","isClick":true},{"id":"7_58_13830","label":"平遥县香乐乡香乐村卫生室","votes":"","isClick":true},{"id":"7_58_13831","label":"平遥县香乐乡陶屯村卫生室","votes":"","isClick":true},{"id":"7_58_13832","label":"平遥县香乐乡北薛靳村卫生室","votes":"","isClick":true},{"id":"7_58_13833","label":"平遥县香乐乡南薛靳村卫生室","votes":"","isClick":true},{"id":"7_58_13834","label":"平遥县中都乡卫生院","votes":"","isClick":true},{"id":"7_58_13835","label":"平遥县中都乡东达蒲村卫生室","votes":"","isClick":true},{"id":"7_58_13836","label":"平遥县中都乡西达蒲村卫生室","votes":"","isClick":true},{"id":"7_58_13837","label":"平遥县中都乡东庄村卫生室","votes":"","isClick":true},{"id":"7_58_13838","label":"平遥县中都乡西庄村卫生室","votes":"","isClick":true},{"id":"7_58_13839","label":"平遥县中都乡梁周村卫生室","votes":"","isClick":true},{"id":"7_58_13840","label":"平遥县中都乡北良如村卫生室","votes":"","isClick":true},{"id":"7_58_13841","label":"平遥县中都乡侯冀村卫生室","votes":"","isClick":true},{"id":"7_58_13842","label":"平遥县中都乡北姚村卫生室","votes":"","isClick":true},{"id":"7_58_13843","label":"平遥县中都乡道虎壁村卫生室","votes":"","isClick":true},{"id":"7_58_13844","label":"平遥县中都乡南姚村卫生室","votes":"","isClick":true},{"id":"7_58_13845","label":"平遥县中都乡桥头村卫生室","votes":"","isClick":true},{"id":"7_58_13846","label":"平遥县中都乡南三狼村卫生室","votes":"","isClick":true},{"id":"7_58_13847","label":"平遥县中都乡曹村卫生室","votes":"","isClick":true},{"id":"7_58_13848","label":"平遥县中都乡杜村卫生室","votes":"","isClick":true},{"id":"7_58_13849","label":"平遥县中都乡北三狼村卫生室","votes":"","isClick":true},{"id":"7_58_13850","label":"平遥县中都乡梁赵村卫生室","votes":"","isClick":true},{"id":"7_58_13851","label":"平遥县中都乡南良如村卫生室","votes":"","isClick":true},{"id":"7_58_13852","label":"平遥县中都乡西胡村卫生室","votes":"","isClick":true},{"id":"7_58_13853","label":"平遥县襄垣乡卫生院","votes":"","isClick":true},{"id":"7_58_13854","label":"平遥县襄垣乡襄垣村卫生室","votes":"","isClick":true},{"id":"7_58_13855","label":"平遥县襄垣乡郝桥村卫生室","votes":"","isClick":true},{"id":"7_58_13856","label":"平遥县襄垣乡白城村卫生室","votes":"","isClick":true},{"id":"7_58_13857","label":"平遥县襄垣乡府底村卫生室","votes":"","isClick":true},{"id":"7_58_13858","label":"平遥县襄垣乡桑冀村卫生室","votes":"","isClick":true},{"id":"7_58_13859","label":"平遥县襄垣乡郝开村卫生室","votes":"","isClick":true},{"id":"7_58_13860","label":"平遥县襄垣乡罗鸣村卫生室","votes":"","isClick":true},{"id":"7_58_13861","label":"平遥县襄垣乡郝温村卫生室","votes":"","isClick":true},{"id":"7_58_13862","label":"平遥县襄垣乡长则村卫生室","votes":"","isClick":true},{"id":"7_58_13863","label":"平遥县襄垣乡下汪村卫生室","votes":"","isClick":true},{"id":"7_58_13864","label":"平遥县襄垣乡梁官村卫生室","votes":"","isClick":true},{"id":"7_58_13865","label":"平遥县襄垣乡桃城村卫生室","votes":"","isClick":true},{"id":"7_58_13866","label":"平遥县襄垣乡良合村卫生室","votes":"","isClick":true},{"id":"7_58_13867","label":"平遥县襄垣乡郝洞村卫生室","votes":"","isClick":true},{"id":"7_58_13868","label":"平遥县襄垣乡曹冀村卫生室","votes":"","isClick":true},{"id":"7_58_13869","label":"平遥县襄垣乡林盛村卫生室","votes":"","isClick":true},{"id":"7_58_13870","label":"平遥县襄垣乡柏森村卫生室","votes":"","isClick":true},{"id":"7_58_13871","label":"平遥县襄垣乡郝家堡村卫生室","votes":"","isClick":true},{"id":"7_58_13872","label":"平遥县襄垣乡府底村东善信卫生室","votes":"","isClick":true},{"id":"7_58_13873","label":"平遥县段村中心卫生院","votes":"","isClick":true},{"id":"7_58_13874","label":"平遥县段村镇南羌村卫生室","votes":"","isClick":true},{"id":"7_58_13875","label":"平遥县段村镇希贤村卫生室","votes":"","isClick":true},{"id":"7_58_13876","label":"平遥县段村镇文祠神村卫生室","votes":"","isClick":true},{"id":"7_58_13877","label":"平遥县段村镇阮庄村卫生室","votes":"","isClick":true},{"id":"7_58_13878","label":"平遥县段村镇南常村卫生室","votes":"","isClick":true},{"id":"7_58_13879","label":"平遥县段村镇陈西村卫生室","votes":"","isClick":true},{"id":"7_58_13880","label":"平遥县段村镇旭庄村卫生室","votes":"","isClick":true},{"id":"7_58_13881","label":"平遥县段村镇北羌村卫生室","votes":"","isClick":true},{"id":"7_58_13882","label":"平遥县段村镇七洞村卫生室","votes":"","isClick":true},{"id":"7_58_13883","label":"平遥县段村镇东安社村卫生室","votes":"","isClick":true},{"id":"7_58_13884","label":"平遥县段村镇马壁村卫生室","votes":"","isClick":true},{"id":"7_58_13885","label":"平遥县段村中心卫生院普洞卫生室","votes":"","isClick":true},{"id":"7_58_13886","label":"平遥县段村镇廉庄村卫生室","votes":"","isClick":true},{"id":"7_58_13887","label":"平遥县段村镇希尧村卫生室","votes":"","isClick":true},{"id":"7_58_13888","label":"平遥县段村镇堡和村卫生室","votes":"","isClick":true},{"id":"7_58_13889","label":"平遥县段村镇段村卫生室","votes":"","isClick":true},{"id":"7_58_13890","label":"平遥县段村镇横坡村卫生室","votes":"","isClick":true},{"id":"7_58_13891","label":"平遥县段村镇西安社村卫生室","votes":"","isClick":true},{"id":"7_58_13892","label":"平遥县段村镇弓村卫生室","votes":"","isClick":true},{"id":"7_58_13893","label":"平遥县段村镇北常村卫生室","votes":"","isClick":true},{"id":"7_58_13894","label":"平遥县卜宜乡卫生院","votes":"","isClick":true},{"id":"7_58_13895","label":"平遥县卜宜乡石城村卫生室","votes":"","isClick":true},{"id":"7_58_13896","label":"平遥县卜宜乡武村卫生室","votes":"","isClick":true},{"id":"7_58_13897","label":"平遥县卜宜乡敖坡村卫生室","votes":"","isClick":true},{"id":"7_58_13898","label":"平遥县卜宜乡林泉村卫生室","votes":"","isClick":true},{"id":"7_58_13899","label":"平遥县卜宜乡南王家庄村卫生室","votes":"","isClick":true},{"id":"7_58_13900","label":"平遥县卜宜乡梁家滩村卫生室","votes":"","isClick":true},{"id":"7_58_13901","label":"平遥县卜宜乡靳村卫生室","votes":"","isClick":true},{"id":"7_58_13902","label":"平遥县卜宜乡西坡村卫生室","votes":"","isClick":true},{"id":"7_58_13903","label":"平遥县卜宜乡东胡村卫生室","votes":"","isClick":true},{"id":"7_58_13904","label":"平遥县卜宜乡西卜宜村卫生室","votes":"","isClick":true},{"id":"7_58_13905","label":"平遥县卜宜乡枣树坪村卫生室","votes":"","isClick":true},{"id":"7_58_13906","label":"平遥县卜宜乡路牛村卫生室","votes":"","isClick":true},{"id":"7_58_13907","label":"平遥县卜宜乡明子村卫生室","votes":"","isClick":true},{"id":"7_58_13908","label":"平遥县卜宜乡东坡村卫生室","votes":"","isClick":true},{"id":"7_58_13909","label":"平遥县卜宜乡青龙村卫生室","votes":"","isClick":true},{"id":"7_58_13910","label":"平遥县卜宜乡果子沟村卫生室","votes":"","isClick":true},{"id":"7_58_13911","label":"平遥县卜宜乡落邑村卫生室","votes":"","isClick":true},{"id":"7_58_13912","label":"平遥县卜宜乡北石渠村卫生室","votes":"","isClick":true},{"id":"7_58_13913","label":"平遥县卜宜乡南杜家庄村卫生室","votes":"","isClick":true},{"id":"7_58_13914","label":"平遥县卜宜乡南石渠村卫生室","votes":"","isClick":true},{"id":"7_58_13915","label":"平遥县卜宜乡小胡村卫生室","votes":"","isClick":true},{"id":"7_58_13916","label":"平遥县卜宜乡永城村卫生室","votes":"","isClick":true},{"id":"7_58_13917","label":"平遥县卜宜乡梁家寨村卫生室","votes":"","isClick":true},{"id":"7_58_13918","label":"平遥县卜宜乡神南村卫生室","votes":"","isClick":true},{"id":"7_58_13919","label":"平遥县卜宜乡东卜宜村卫生室","votes":"","isClick":true},{"id":"7_58_13920","label":"平遥县卜宜乡范村卫生室","votes":"","isClick":true},{"id":"7_58_13921","label":"平遥县卜宜乡军寨村卫生室","votes":"","isClick":true},{"id":"7_58_13922","label":"平遥县孟山卫生院","votes":"","isClick":true},{"id":"7_58_13923","label":"平遥县孟山乡昌源庄村卫生室","votes":"","isClick":true},{"id":"7_58_13924","label":"平遥县孟山乡贾封村卫生室","votes":"","isClick":true},{"id":"7_58_13925","label":"平遥县孟山乡康家庄村卫生室","votes":"","isClick":true},{"id":"7_58_13926","label":"平遥县孟山乡安洼村卫生室","votes":"","isClick":true},{"id":"7_58_13927","label":"平遥县孟山乡石圐圙村卫生室","votes":"","isClick":true},{"id":"7_58_13928","label":"平遥县孟山乡花沟村卫生室","votes":"","isClick":true},{"id":"7_58_13929","label":"平遥县孟山乡魏家庄村卫生室","votes":"","isClick":true},{"id":"7_58_13930","label":"平遥县孟山乡二郎村卫生室","votes":"","isClick":true},{"id":"7_58_13931","label":"平遥县孟山乡下石庵村卫生室","votes":"","isClick":true},{"id":"7_58_13932","label":"平遥县孟山乡石家坡村卫生室","votes":"","isClick":true},{"id":"7_58_13933","label":"平遥县东泉中心卫生院","votes":"","isClick":true},{"id":"7_58_13934","label":"平遥县东泉镇东戈山村卫生室","votes":"","isClick":true},{"id":"7_58_13935","label":"平遥县东泉镇圪塔村卫生室","votes":"","isClick":true},{"id":"7_58_13936","label":"平遥县东泉镇赵壁村卫生室","votes":"","isClick":true},{"id":"7_58_13937","label":"平遥县东泉镇遮胡村卫生室","votes":"","isClick":true},{"id":"7_58_13938","label":"平遥县东泉镇水磨头村卫生室","votes":"","isClick":true},{"id":"7_58_13939","label":"平遥县东泉镇千庄村卫生室","votes":"","isClick":true},{"id":"7_58_13940","label":"平遥县东泉镇南湖村卫生室","votes":"","isClick":true},{"id":"7_58_13941","label":"平遥县东泉镇常村卫生室","votes":"","isClick":true},{"id":"7_58_13942","label":"平遥县东泉镇木瓜村卫生室","votes":"","isClick":true},{"id":"7_58_13943","label":"平遥县东泉镇东源祠村卫生室","votes":"","isClick":true},{"id":"7_58_13944","label":"平遥县东泉镇修德村卫生室","votes":"","isClick":true},{"id":"7_58_13945","label":"平遥县东泉镇彭坡头村卫生室","votes":"","isClick":true},{"id":"7_58_13946","label":"平遥县东泉镇上庄村卫生室","votes":"","isClick":true},{"id":"7_58_13947","label":"平遥县东泉镇东泉村卫生室","votes":"","isClick":true},{"id":"7_58_13948","label":"平遥县东泉镇梅槐头村卫生室","votes":"","isClick":true},{"id":"7_58_13949","label":"平遥县东泉镇东赵村卫生室","votes":"","isClick":true},{"id":"7_58_13950","label":"平遥县东泉镇南岭底村卫生室","votes":"","isClick":true},{"id":"7_58_13951","label":"平遥县东泉镇西戈山村卫生室","votes":"","isClick":true},{"id":"7_58_13952","label":"平遥县杜家庄乡卫生院","votes":"","isClick":true},{"id":"7_58_13953","label":"平遥县杜家庄乡东良庄村卫生室","votes":"","isClick":true},{"id":"7_58_13954","label":"平遥县杜家庄乡西良庄村卫生室","votes":"","isClick":true},{"id":"7_58_13955","label":"平遥县杜家庄乡南良庄村卫生室","votes":"","isClick":true},{"id":"7_58_13956","label":"平遥县杜家庄乡苏家堡村卫生室","votes":"","isClick":true},{"id":"7_58_13957","label":"平遥县杜家庄乡闫长头村卫生室","votes":"","isClick":true},{"id":"7_58_13958","label":"平遥县杜家庄乡杜家庄村卫生室","votes":"","isClick":true},{"id":"7_58_13959","label":"平遥县杜家庄乡回回堡村卫生室","votes":"","isClick":true},{"id":"7_58_13960","label":"平遥县杜家庄乡仁庄村卫生室","votes":"","isClick":true},{"id":"7_58_13961","label":"平遥县杜家庄乡梧桐村卫生室","votes":"","isClick":true},{"id":"7_58_13962","label":"平遥县杜家庄乡东凤落村卫生室","votes":"","isClick":true},{"id":"7_58_13963","label":"平遥县杜家庄乡西凤落村卫生室","votes":"","isClick":true},{"id":"7_58_13964","label":"平遥县城东社区卫生服务中心","votes":"","isClick":true},{"id":"7_58_13965","label":"平遥县古城社区卫生服务中心","votes":"","isClick":true},{"id":"7_58_13966","label":"平遥县洪善中心卫生院沿村堡卫生站","votes":"","isClick":true},{"id":"7_58_13967","label":"平遥县洪善镇五里庄村卫生室","votes":"","isClick":true},{"id":"7_58_13968","label":"平遥县洪善镇沿村堡村卫生室","votes":"","isClick":true},{"id":"7_58_13969","label":"平遥县洪善镇钦贤村卫生室","votes":"","isClick":true},{"id":"7_58_13970","label":"平遥县洪善镇京陵村卫生室","votes":"","isClick":true},{"id":"7_58_13971","label":"平遥县洪善镇东庄村卫生室","votes":"","isClick":true},{"id":"7_58_13972","label":"平遥县洪善镇冀郭村卫生室","votes":"","isClick":true},{"id":"7_58_13973","label":"平遥县洪善镇东大闫村卫生室","votes":"","isClick":true},{"id":"7_58_13974","label":"平遥县洪善镇新胜村卫生室","votes":"","isClick":true},{"id":"7_58_13975","label":"平遥县洪善镇尹村卫生室","votes":"","isClick":true},{"id":"7_58_13976","label":"平遥县洪善镇小沿村卫生室","votes":"","isClick":true},{"id":"7_58_13977","label":"平遥县洪善镇西大闫村卫生室","votes":"","isClick":true},{"id":"7_58_13978","label":"平遥县岳壁乡卫生院梁坡底卫生站","votes":"","isClick":true},{"id":"7_58_13979","label":"平遥县岳壁乡南西泉村卫生室","votes":"","isClick":true},{"id":"7_58_13980","label":"平遥县岳壁乡北西泉村卫生室","votes":"","isClick":true},{"id":"7_58_13981","label":"平遥县岳壁乡偏城村卫生室","votes":"","isClick":true},{"id":"7_58_13982","label":"平遥县岳壁乡下沟西村卫生室","votes":"","isClick":true},{"id":"7_58_13983","label":"平遥县岳壁乡梁坡底村卫生室","votes":"","isClick":true},{"id":"7_58_13984","label":"平遥县岳壁乡上五村卫生室","votes":"","isClick":true},{"id":"7_58_13985","label":"平遥县朱坑中心卫生院辛村卫生站","votes":"","isClick":true},{"id":"7_58_13986","label":"平遥县朱坑乡乔家山村卫生室","votes":"","isClick":true},{"id":"7_58_13987","label":"平遥县朱坑乡侯壁村卫生室","votes":"","isClick":true},{"id":"7_58_13988","label":"平遥县朱坑乡六河村卫生室","votes":"","isClick":true},{"id":"7_58_13989","label":"平遥县朱坑乡郭休村卫生室","votes":"","isClick":true},{"id":"7_58_13990","label":"平遥县朱坑乡龙胜村卫生室","votes":"","isClick":true},{"id":"7_58_13991","label":"平遥县朱坑乡辛村卫生室","votes":"","isClick":true},{"id":"7_58_13992","label":"平遥县朱坑乡青村卫生室","votes":"","isClick":true},{"id":"7_58_13993","label":"平遥县朱坑乡丰盛村卫生室","votes":"","isClick":true},{"id":"7_58_13994","label":"平遥县朱坑乡喜村卫生室","votes":"","isClick":true},{"id":"7_58_13995","label":"平遥县香乐乡卫生院西王智卫生站","votes":"","isClick":true},{"id":"7_58_13996","label":"平遥县香乐乡罗城村卫生室","votes":"","isClick":true},{"id":"7_58_13997","label":"平遥县香乐乡西王智村卫生室","votes":"","isClick":true},{"id":"7_58_13998","label":"平遥县香乐乡大羌村卫生室","votes":"","isClick":true},{"id":"7_58_13999","label":"平遥县香乐乡郝家庄村卫生室","votes":"","isClick":true},{"id":"7_58_14000","label":"平遥县香乐乡赵家堡村卫生室","votes":"","isClick":true},{"id":"7_58_14001","label":"平遥县香乐乡中官地村卫生室","votes":"","isClick":true},{"id":"7_58_14002","label":"平遥县香乐乡薛贤村卫生室","votes":"","isClick":true},{"id":"7_58_14003","label":"平遥县香乐乡南官地村卫生室","votes":"","isClick":true},{"id":"7_58_14004","label":"平遥县香乐乡北官地村卫生室","votes":"","isClick":true},{"id":"7_58_14005","label":"平遥县香乐乡三家村卫生室","votes":"","isClick":true},{"id":"7_58_14006","label":"平遥县香乐乡西羌村卫生室","votes":"","isClick":true},{"id":"7_58_14007","label":"平遥县宁固中心卫生院净化卫生站","votes":"","isClick":true},{"id":"7_58_14008","label":"宁固镇净化村卫生室","votes":"","isClick":true},{"id":"7_58_14009","label":"平遥县宁固镇营里村卫生室","votes":"","isClick":true},{"id":"7_58_14010","label":"平遥县宁固镇曹家堡村卫生室","votes":"","isClick":true},{"id":"7_58_14011","label":"平遥县宁固镇魏乐村卫生室","votes":"","isClick":true},{"id":"7_58_14012","label":"平遥县宁固镇丰依村卫生室","votes":"","isClick":true},{"id":"7_58_14013","label":"平遥县宁固镇王郭村卫生室","votes":"","isClick":true},{"id":"7_58_14014","label":"平遥县宁固镇油房堡村卫生室","votes":"","isClick":true},{"id":"7_58_14015","label":"平遥县宁固镇苏封村卫生室","votes":"","isClick":true},{"id":"7_58_14016","label":"平遥县宁固镇岳封村卫生室","votes":"","isClick":true},{"id":"7_58_14017","label":"平遥县宁固镇王智村卫生室","votes":"","isClick":true},{"id":"7_58_14018","label":"平遥县宁固镇鱼市村卫生室","votes":"","isClick":true},{"id":"7_58_14019","label":"平遥县宁固镇新建村卫生室","votes":"","isClick":true},{"id":"7_58_14020","label":"平遥县宁固镇芦村卫生室","votes":"","isClick":true},{"id":"7_58_14021","label":"平遥县南政乡卫生院王家庄卫生站","votes":"","isClick":true},{"id":"7_58_14022","label":"平遥县南政乡西堡村卫生室","votes":"","isClick":true},{"id":"7_58_14023","label":"平遥县南政乡小王家庄村卫生室","votes":"","isClick":true},{"id":"7_58_14024","label":"平遥县南政乡李家桥村卫生室","votes":"","isClick":true},{"id":"7_58_14025","label":"平遥县南政乡贾家庄村卫生室","votes":"","isClick":true},{"id":"7_58_14026","label":"平遥县南政乡东游驾村卫生室","votes":"","isClick":true},{"id":"7_58_14027","label":"平遥县南政乡道备村卫生室","votes":"","isClick":true},{"id":"7_58_14028","label":"平遥县南政乡蒋家堡村卫生室","votes":"","isClick":true},{"id":"7_58_14029","label":"平遥县南政乡小徐村卫生室","votes":"","isClick":true},{"id":"7_58_14030","label":"平遥县南政乡王家庄村卫生室","votes":"","isClick":true},{"id":"7_58_14031","label":"平遥县南政乡田家堡村卫生室","votes":"","isClick":true},{"id":"7_58_14032","label":"平遥县南政乡西游驾村卫生室","votes":"","isClick":true},{"id":"7_58_14033","label":"平遥县疾病预防控制中心门诊","votes":"","isClick":true},{"id":"7_58_14034","label":"平遥县计划生育妇幼保健服务中心","votes":"","isClick":true},{"id":"7_58_14035","label":"平遥县卫生监督所","votes":"","isClick":true}]}