{"data":[{"id":"9_86_21469","label":"偏关县窑头乡卫生院","votes":"","isClick":true},{"id":"9_86_21470","label":"窑头乡石门庄村卫生室","votes":"","isClick":true},{"id":"9_86_21471","label":"窑头乡何家沟村卫生室","votes":"","isClick":true},{"id":"9_86_21472","label":"窑头乡沙圪旦村卫生室","votes":"","isClick":true},{"id":"9_86_21473","label":"窑头乡八打洼村卫生室","votes":"","isClick":true},{"id":"9_86_21474","label":"窑头乡堡子湾村卫生室","votes":"","isClick":true},{"id":"9_86_21475","label":"窑头乡表干坡村卫生室","votes":"","isClick":true},{"id":"9_86_21476","label":"窑头乡阳坡泉村卫生室","votes":"","isClick":true},{"id":"9_86_21477","label":"窑头乡沙坡村卫生室","votes":"","isClick":true},{"id":"9_86_21478","label":"窑头乡岳家村卫生室","votes":"","isClick":true},{"id":"9_86_21479","label":"窑头乡腰铺村卫生室","votes":"","isClick":true},{"id":"9_86_21480","label":"窑头乡高家埝村卫生室","votes":"","isClick":true},{"id":"9_86_21481","label":"窑头乡响水村卫生室","votes":"","isClick":true},{"id":"9_86_21482","label":"窑头乡南窑头村卫生室","votes":"","isClick":true},{"id":"9_86_21483","label":"窑头乡楼子沟村卫生室","votes":"","isClick":true},{"id":"9_86_21484","label":"窑头乡火头村卫生室","votes":"","isClick":true},{"id":"9_86_21485","label":"窑头乡张家埝村卫生室","votes":"","isClick":true},{"id":"9_86_21486","label":"窑头乡阳坡店村卫生室","votes":"","isClick":true},{"id":"9_86_21487","label":"窑头乡王家坪村卫生室","votes":"","isClick":true},{"id":"9_86_21488","label":"窑头乡宋家畔次卫生室","votes":"","isClick":true},{"id":"9_86_21489","label":"窑头乡移民村卫生室","votes":"","isClick":true},{"id":"9_86_21490","label":"窑头乡铁驼村卫生室","votes":"","isClick":true},{"id":"9_86_21491","label":"偏关县陈家营乡卫生院","votes":"","isClick":true},{"id":"9_86_21492","label":"坝子山村卫生室","votes":"","isClick":true},{"id":"9_86_21493","label":"张家山村卫生室","votes":"","isClick":true},{"id":"9_86_21494","label":"常家尧村卫生室","votes":"","isClick":true},{"id":"9_86_21495","label":"辛庄窝村卫生室","votes":"","isClick":true},{"id":"9_86_21496","label":"柳树庄窝村卫生室","votes":"","isClick":true},{"id":"9_86_21497","label":"刘家窑村卫生室","votes":"","isClick":true},{"id":"9_86_21498","label":"油房头村卫生室","votes":"","isClick":true},{"id":"9_86_21499","label":"杨家营村卫生室","votes":"","isClick":true},{"id":"9_86_21500","label":"阎家贝村卫生室","votes":"","isClick":true},{"id":"9_86_21501","label":"八柳树村卫生室","votes":"","isClick":true},{"id":"9_86_21502","label":"曲家湾村卫生室","votes":"","isClick":true},{"id":"9_86_21503","label":"黄家营村卫生室","votes":"","isClick":true},{"id":"9_86_21504","label":"黑山村卫生室","votes":"","isClick":true},{"id":"9_86_21505","label":"阴窝沟村卫生室","votes":"","isClick":true},{"id":"9_86_21506","label":"小斗沟村卫生室","votes":"","isClick":true},{"id":"9_86_21507","label":"高家湾村卫生室","votes":"","isClick":true},{"id":"9_86_21508","label":"西庄子村卫生室","votes":"","isClick":true},{"id":"9_86_21509","label":"石沟子村卫生室","votes":"","isClick":true},{"id":"9_86_21510","label":"天洼村卫生室","votes":"","isClick":true},{"id":"9_86_21511","label":"马站村卫生室","votes":"","isClick":true},{"id":"9_86_21512","label":"偏关县水泉乡卫生院","votes":"","isClick":true},{"id":"9_86_21513","label":"水泉乡南海子村卫生室","votes":"","isClick":true},{"id":"9_86_21514","label":"水泉乡张岭沟村卫生室","votes":"","isClick":true},{"id":"9_86_21515","label":"水泉乡达连庄窝村卫生室","votes":"","isClick":true},{"id":"9_86_21516","label":"水泉乡高峁村卫生室","votes":"","isClick":true},{"id":"9_86_21517","label":"水泉乡百草坪村卫生室","votes":"","isClick":true},{"id":"9_86_21518","label":"水泉乡弓家贝村卫生室","votes":"","isClick":true},{"id":"9_86_21519","label":"水泉乡七家坪村卫生室","votes":"","isClick":true},{"id":"9_86_21520","label":"水泉乡池家塔村卫生室","votes":"","isClick":true},{"id":"9_86_21521","label":"水泉乡刘家咀村卫生室","votes":"","isClick":true},{"id":"9_86_21522","label":"水泉乡麦绿坡村卫生室","votes":"","isClick":true},{"id":"9_86_21523","label":"偏关县老营镇卫生院","votes":"","isClick":true},{"id":"9_86_21524","label":"偏关县老营镇上土寨村卫生室","votes":"","isClick":true},{"id":"9_86_21525","label":"偏关县老营镇窄沟村卫生室","votes":"","isClick":true},{"id":"9_86_21526","label":"偏关县老营镇银子咀村卫生室","votes":"","isClick":true},{"id":"9_86_21527","label":"偏关县老营镇鸭子坪村卫生室","votes":"","isClick":true},{"id":"9_86_21528","label":"偏关县老营镇下土寨村卫生室","votes":"","isClick":true},{"id":"9_86_21529","label":"偏关县老营镇西庄子村卫生室","votes":"","isClick":true},{"id":"9_86_21530","label":"偏关县老营镇武家庄窝村卫生室","votes":"","isClick":true},{"id":"9_86_21531","label":"偏关县老营镇史家圪台村卫生室","votes":"","isClick":true},{"id":"9_86_21532","label":"偏关县老营镇木瓜贝村卫生室","votes":"","isClick":true},{"id":"9_86_21533","label":"偏关县老营镇马肚梁村卫生室","votes":"","isClick":true},{"id":"9_86_21534","label":"偏关县老营镇教儿埝村卫生室","votes":"","isClick":true},{"id":"9_86_21535","label":"偏关县老营镇贾堡村卫生室","votes":"","isClick":true},{"id":"9_86_21536","label":"偏关县老营镇冯家窑子村卫生室","votes":"","isClick":true},{"id":"9_86_21537","label":"偏关县老营镇方城村卫生室","votes":"","isClick":true},{"id":"9_86_21538","label":"偏关县老营镇大河湾村卫生室","votes":"","isClick":true},{"id":"9_86_21539","label":"偏关县老营镇岩头寺村卫生室","votes":"","isClick":true},{"id":"9_86_21540","label":"偏关县老营镇阴窝沟村卫生室","votes":"","isClick":true},{"id":"9_86_21541","label":"偏关县老营镇段家沟村卫生室","votes":"","isClick":true},{"id":"9_86_21542","label":"偏关县窑头乡卫生院大石洼分院","votes":"","isClick":true},{"id":"9_86_21543","label":"偏关县窑头乡闫家洼村卫生室","votes":"","isClick":true},{"id":"9_86_21544","label":"偏关县窑头乡高峁梁村卫生室","votes":"","isClick":true},{"id":"9_86_21545","label":"偏关县窑头乡韩昌沟村卫生室","votes":"","isClick":true},{"id":"9_86_21546","label":"偏关县窑头乡霍家沟村卫生室","votes":"","isClick":true},{"id":"9_86_21547","label":"偏关县窑头乡抢风梁村卫生室","votes":"","isClick":true},{"id":"9_86_21548","label":"偏关县窑头乡黄树坪村卫生室","votes":"","isClick":true},{"id":"9_86_21549","label":"偏关县窑头乡小石洼卫生室","votes":"","isClick":true},{"id":"9_86_21550","label":"偏关县窑头乡天洼村卫生室","votes":"","isClick":true},{"id":"9_86_21551","label":"偏关县窑头乡光明村卫生室","votes":"","isClick":true},{"id":"9_86_21552","label":"偏关县窑头乡沙埝村卫生室","votes":"","isClick":true},{"id":"9_86_21553","label":"偏关县楼沟乡卫生院","votes":"","isClick":true},{"id":"9_86_21554","label":"楼沟乡迤西村卫生室","votes":"","isClick":true},{"id":"9_86_21555","label":"楼沟乡庄子洼村卫生室","votes":"","isClick":true},{"id":"9_86_21556","label":"楼沟乡卡坡村卫生室","votes":"","isClick":true},{"id":"9_86_21557","label":"楼沟乡小村村卫生室","votes":"","isClick":true},{"id":"9_86_21558","label":"楼沟乡咀上村卫生室","votes":"","isClick":true},{"id":"9_86_21559","label":"楼沟乡磨老洼村卫生室","votes":"","isClick":true},{"id":"9_86_21560","label":"楼沟乡刘家沟村卫生室","votes":"","isClick":true},{"id":"9_86_21561","label":"楼沟乡柏家咀村卫生室","votes":"","isClick":true},{"id":"9_86_21562","label":"楼沟乡下川村卫生室","votes":"","isClick":true},{"id":"9_86_21563","label":"楼沟乡吴城村卫生室","votes":"","isClick":true},{"id":"9_86_21564","label":"楼沟乡红崖上村卫生室","votes":"","isClick":true},{"id":"9_86_21565","label":"楼沟乡新庄窝村卫生室","votes":"","isClick":true},{"id":"9_86_21566","label":"楼沟乡周家山村卫生室","votes":"","isClick":true},{"id":"9_86_21567","label":"楼沟乡碾子梁村卫生室","votes":"","isClick":true},{"id":"9_86_21568","label":"楼沟乡马圈咀卫生室","votes":"","isClick":true},{"id":"9_86_21569","label":"楼沟乡上铺村卫生室","votes":"","isClick":true},{"id":"9_86_21570","label":"楼沟乡柳介沟村卫生室","votes":"","isClick":true},{"id":"9_86_21571","label":"楼沟乡三台梁村卫生室","votes":"","isClick":true},{"id":"9_86_21572","label":"楼沟乡柳埝坪村卫生室","votes":"","isClick":true},{"id":"9_86_21573","label":"楼沟乡豆家深埝村卫生室","votes":"","isClick":true},{"id":"9_86_21574","label":"楼沟乡韩家畔村卫生室","votes":"","isClick":true},{"id":"9_86_21575","label":"楼沟乡张家坪村卫生室","votes":"","isClick":true},{"id":"9_86_21576","label":"楼沟乡尹家埝村卫生室","votes":"","isClick":true},{"id":"9_86_21577","label":"偏关县楼沟乡卫生院曹家村分院","votes":"","isClick":true},{"id":"9_86_21578","label":"偏关县楼沟乡东寨村卫生室","votes":"","isClick":true},{"id":"9_86_21579","label":"偏关县楼沟乡西寨村卫生室","votes":"","isClick":true},{"id":"9_86_21580","label":"偏关县楼沟乡石家洼村卫生室","votes":"","isClick":true},{"id":"9_86_21581","label":"偏关县楼沟乡上固佐村卫生室","votes":"","isClick":true},{"id":"9_86_21582","label":"偏关县楼沟乡下固佐村卫生室","votes":"","isClick":true},{"id":"9_86_21583","label":"偏关县楼沟乡后尧上村卫生室","votes":"","isClick":true},{"id":"9_86_21584","label":"偏关县楼沟乡圪坨村卫生室","votes":"","isClick":true},{"id":"9_86_21585","label":"偏关县楼沟乡栢杆寺村卫生室","votes":"","isClick":true},{"id":"9_86_21586","label":"偏关县楼沟乡甲咀村卫生室","votes":"","isClick":true},{"id":"9_86_21587","label":"偏关县楼沟乡苍黄坪村卫生室","votes":"","isClick":true},{"id":"9_86_21588","label":"偏关县楼沟乡石碣上村卫生室","votes":"","isClick":true},{"id":"9_86_21589","label":"偏关县楼沟乡李家山村卫生室","votes":"","isClick":true},{"id":"9_86_21590","label":"偏关县楼沟乡柳沟村卫生室","votes":"","isClick":true},{"id":"9_86_21591","label":"偏关县楼沟乡王家山村卫生室","votes":"","isClick":true},{"id":"9_86_21592","label":"偏关县楼沟乡冉家营村卫生室","votes":"","isClick":true},{"id":"9_86_21593","label":"偏关县楼沟乡辛庄子村卫生室","votes":"","isClick":true},{"id":"9_86_21594","label":"偏关县楼沟乡海子贝村卫生室","votes":"","isClick":true},{"id":"9_86_21595","label":"偏关县楼沟乡庄子寺村卫生室","votes":"","isClick":true},{"id":"9_86_21596","label":"偏关县楼沟乡刘满庄村卫生室","votes":"","isClick":true},{"id":"9_86_21597","label":"偏关县尚峪乡卫生院","votes":"","isClick":true},{"id":"9_86_21598","label":"偏关县尚峪乡百草坪村卫生室","votes":"","isClick":true},{"id":"9_86_21599","label":"偏关县尚峪乡曹家沟村卫生室","votes":"","isClick":true},{"id":"9_86_21600","label":"偏关县尚峪乡庄王村卫生室","votes":"","isClick":true},{"id":"9_86_21601","label":"偏关县尚峪乡安儿上村卫生室","votes":"","isClick":true},{"id":"9_86_21602","label":"偏关县尚峪乡东尚峪村卫生室","votes":"","isClick":true},{"id":"9_86_21603","label":"偏关县尚峪乡甘沟村卫生室","votes":"","isClick":true},{"id":"9_86_21604","label":"偏关县尚峪乡长安镇村卫生室","votes":"","isClick":true},{"id":"9_86_21605","label":"偏关县尚峪乡甘曹咀村卫生室","votes":"","isClick":true},{"id":"9_86_21606","label":"偏关县尚峪乡西峪村卫生室","votes":"","isClick":true},{"id":"9_86_21607","label":"偏关县尚峪乡赵家沟村卫生室","votes":"","isClick":true},{"id":"9_86_21608","label":"偏关县尚峪乡瑞家沟村卫生室","votes":"","isClick":true},{"id":"9_86_21609","label":"偏关县尚峪乡草场村卫生室","votes":"","isClick":true},{"id":"9_86_21610","label":"偏关县尚峪乡大泉上村卫生室","votes":"","isClick":true},{"id":"9_86_21611","label":"偏关县尚峪乡碾儿沟村卫生室","votes":"","isClick":true},{"id":"9_86_21612","label":"偏关县尚峪乡豆儿沟村卫生室","votes":"","isClick":true},{"id":"9_86_21613","label":"偏关县南堡子乡卫生院","votes":"","isClick":true},{"id":"9_86_21614","label":"南堡子乡南沟村卫生室","votes":"","isClick":true},{"id":"9_86_21615","label":"南堡子乡上纸房村卫生室","votes":"","isClick":true},{"id":"9_86_21616","label":"南堡子乡教子沟村卫生室","votes":"","isClick":true},{"id":"9_86_21617","label":"南堡子乡双寨村卫生室","votes":"","isClick":true},{"id":"9_86_21618","label":"南堡子乡上井坪村卫生室","votes":"","isClick":true},{"id":"9_86_21619","label":"南堡子乡车道坡村卫生室","votes":"","isClick":true},{"id":"9_86_21620","label":"南堡子乡黑家庄村卫生室","votes":"","isClick":true},{"id":"9_86_21621","label":"南堡子乡大庄窝村卫生室","votes":"","isClick":true},{"id":"9_86_21622","label":"南堡子乡小庄窝村卫生室","votes":"","isClick":true},{"id":"9_86_21623","label":"南堡子乡张家庄村卫生室","votes":"","isClick":true},{"id":"9_86_21624","label":"南堡子乡下井坪村卫生室","votes":"","isClick":true},{"id":"9_86_21625","label":"南堡子乡南场村卫生室","votes":"","isClick":true},{"id":"9_86_21626","label":"南堡子乡北场村卫生室","votes":"","isClick":true},{"id":"9_86_21627","label":"南堡子乡泉儿上村卫生室","votes":"","isClick":true},{"id":"9_86_21628","label":"南堡子乡大虫岭村卫生室","votes":"","isClick":true},{"id":"9_86_21629","label":"偏关县天峰坪镇卫生院","votes":"","isClick":true},{"id":"9_86_21630","label":"偏关县天峰坪镇寺沟村卫生室","votes":"","isClick":true},{"id":"9_86_21631","label":"偏关县天峰坪镇担水沟村卫生室","votes":"","isClick":true},{"id":"9_86_21632","label":"偏关县天峰坪镇梨园村卫生室","votes":"","isClick":true},{"id":"9_86_21633","label":"偏关县天峰坪镇黑豆埝村卫生室","votes":"","isClick":true},{"id":"9_86_21634","label":"偏关县天峰坪镇吕家窑村卫生室","votes":"","isClick":true},{"id":"9_86_21635","label":"偏关县天峰坪镇闫家沟村卫生室","votes":"","isClick":true},{"id":"9_86_21636","label":"偏关县天峰坪镇杨家岭村卫生室","votes":"","isClick":true},{"id":"9_86_21637","label":"偏关县天峰坪镇小偏头村卫生室","votes":"","isClick":true},{"id":"9_86_21638","label":"偏关县天峰坪镇小蒜沟村卫生室","votes":"","isClick":true},{"id":"9_86_21639","label":"偏关县天峰坪镇柴家岭村卫生室","votes":"","isClick":true},{"id":"9_86_21640","label":"偏关县天峰坪镇欧梨咀村卫生室","votes":"","isClick":true},{"id":"9_86_21641","label":"偏关县天峰坪镇紫金山村卫生室","votes":"","isClick":true},{"id":"9_86_21642","label":"偏关县天峰坪镇天气湾村卫生室","votes":"","isClick":true},{"id":"9_86_21643","label":"偏关县万家寨镇卫生院","votes":"","isClick":true},{"id":"9_86_21644","label":"万家寨镇珍珠庄王村卫生室","votes":"","isClick":true},{"id":"9_86_21645","label":"万家寨镇老牛湾村卫生室","votes":"","isClick":true},{"id":"9_86_21646","label":"万家寨镇沙庄王村卫生室","votes":"","isClick":true},{"id":"9_86_21647","label":"万家寨镇十八盘村卫生室","votes":"","isClick":true},{"id":"9_86_21648","label":"万家寨镇破石槽村卫生室","votes":"","isClick":true},{"id":"9_86_21649","label":"万家寨镇马道咀村卫生室","votes":"","isClick":true},{"id":"9_86_21650","label":"万家寨镇东长咀村卫生室","votes":"","isClick":true},{"id":"9_86_21651","label":"万家寨镇陡咀村卫生室","votes":"","isClick":true},{"id":"9_86_21652","label":"万家寨镇麻地塔村卫生室","votes":"","isClick":true},{"id":"9_86_21653","label":"偏关县万家寨镇卫生院黄龙池分院","votes":"","isClick":true},{"id":"9_86_21654","label":"岳家尧卫生室","votes":"","isClick":true},{"id":"9_86_21655","label":"麦虎村卫生室","votes":"","isClick":true},{"id":"9_86_21656","label":"教官咀村卫生室","votes":"","isClick":true},{"id":"9_86_21657","label":"泉子湾卫生室","votes":"","isClick":true},{"id":"9_86_21658","label":"井儿上村卫生室","votes":"","isClick":true},{"id":"9_86_21659","label":"小刷咀村卫生室","votes":"","isClick":true},{"id":"9_86_21660","label":"柏林茆村卫生室","votes":"","isClick":true},{"id":"9_86_21661","label":"草垛山村卫生室","votes":"","isClick":true},{"id":"9_86_21662","label":"辛尧上村卫生室","votes":"","isClick":true},{"id":"9_86_21663","label":"偏关县新关镇卫生院","votes":"","isClick":true},{"id":"9_86_21664","label":"新关镇高家上石会村卫生室","votes":"","isClick":true},{"id":"9_86_21665","label":"新关镇中关村卫生室","votes":"","isClick":true},{"id":"9_86_21666","label":"新关镇马梁村卫生室","votes":"","isClick":true},{"id":"9_86_21667","label":"新关镇沙石沟村卫生室","votes":"","isClick":true},{"id":"9_86_21668","label":"新关镇上关村卫生室","votes":"","isClick":true},{"id":"9_86_21669","label":"新关镇南城村卫生室","votes":"","isClick":true},{"id":"9_86_21670","label":"新关镇庄王村卫生室","votes":"","isClick":true},{"id":"9_86_21671","label":"新关镇马次梁村卫生室","votes":"","isClick":true},{"id":"9_86_21672","label":"新关镇上尧王坪村卫生室","votes":"","isClick":true},{"id":"9_86_21673","label":"新关镇石洼村卫生室","votes":"","isClick":true},{"id":"9_86_21674","label":"新关镇桑林坡村卫生室","votes":"","isClick":true},{"id":"9_86_21675","label":"新关镇下尧王坪村卫生室","votes":"","isClick":true},{"id":"9_86_21676","label":"新关镇马道村卫生室","votes":"","isClick":true},{"id":"9_86_21677","label":"新关镇阳塔村卫生室","votes":"","isClick":true},{"id":"9_86_21678","label":"新关镇窑子上村卫生室","votes":"","isClick":true},{"id":"9_86_21679","label":"新关镇陈家庄王村卫生室","votes":"","isClick":true},{"id":"9_86_21680","label":"新关镇大红沟村卫生室","votes":"","isClick":true},{"id":"9_86_21681","label":"新关镇营盘梁村卫生室","votes":"","isClick":true},{"id":"9_86_21682","label":"新关镇桃卜村卫生室","votes":"","isClick":true},{"id":"9_86_21683","label":"新关镇泥埝村卫生室","votes":"","isClick":true},{"id":"9_86_21684","label":"新关镇沈家村卫生室","votes":"","isClick":true},{"id":"9_86_21685","label":"新关镇贺家山村卫生室","votes":"","isClick":true},{"id":"9_86_21686","label":"新关镇白龙殿村卫生室","votes":"","isClick":true},{"id":"9_86_21687","label":"新关镇路家窑村卫生室","votes":"","isClick":true},{"id":"9_86_21688","label":"新关镇杨家山村卫生室","votes":"","isClick":true},{"id":"9_86_21689","label":"新关镇闫贵家咀村卫生室","votes":"","isClick":true},{"id":"9_86_21690","label":"新关镇舍身崖村卫生室","votes":"","isClick":true},{"id":"9_86_21691","label":"新关镇磨石滩村卫生室","votes":"","isClick":true},{"id":"9_86_21692","label":"新关镇九崖头村卫生室","votes":"","isClick":true},{"id":"9_86_21693","label":"新关镇西沟村卫生室","votes":"","isClick":true},{"id":"9_86_21694","label":"新关镇磁窑沟村卫生室","votes":"","isClick":true},{"id":"9_86_21695","label":"新关镇路铺村卫生室","votes":"","isClick":true},{"id":"9_86_21696","label":"新关镇王家上石会村卫生室","votes":"","isClick":true},{"id":"9_86_21697","label":"新关镇深埝村卫生室","votes":"","isClick":true},{"id":"9_86_21698","label":"新关镇马家埝村卫生室","votes":"","isClick":true},{"id":"9_86_21699","label":"新关镇北城村卫生室","votes":"","isClick":true},{"id":"9_86_21700","label":"新关镇西关村卫生室","votes":"","isClick":true},{"id":"9_86_21701","label":"新关镇南沟村卫生室","votes":"","isClick":true},{"id":"9_86_21702","label":"偏关县新关镇卫生院马家埝分院","votes":"","isClick":true},{"id":"9_86_21703","label":"偏关县新关镇白海沟村卫生室","votes":"","isClick":true},{"id":"9_86_21704","label":"偏关县新关镇庙儿梁村卫生室","votes":"","isClick":true},{"id":"9_86_21705","label":"偏关县新关镇红庙村卫生室","votes":"","isClick":true},{"id":"9_86_21706","label":"偏关县新关镇大深埝村卫生室","votes":"","isClick":true},{"id":"9_86_21707","label":"偏关县新关镇孤家沟村卫生室","votes":"","isClick":true},{"id":"9_86_21708","label":"偏关县新关镇兴盛庄王村卫生室","votes":"","isClick":true},{"id":"9_86_21709","label":"偏关县新关镇元墩子村卫生室","votes":"","isClick":true},{"id":"9_86_21710","label":"偏关县新关镇刘家湾村卫生室","votes":"","isClick":true},{"id":"9_86_21711","label":"偏关县城区基本公共卫生服务站","votes":"","isClick":true},{"id":"9_86_21712","label":"偏关县疾病控制中心","votes":"","isClick":true},{"id":"9_86_21713","label":"偏关县妇幼和卫生计划生育服务中心","votes":"","isClick":true},{"id":"9_86_21714","label":"偏关县卫生监督所","votes":"","isClick":true}]}